{"active": [{"01.03.2025": "Put22000", "instrumentType": "Index Options", "expiryDate": "06-Mar-2025", "optionType": "Put", "strikePrice": 22000, "openPrice": 22.2, "highPrice": 93.55, "lowPrice": 22.2, "closePrice": 77.2, "prevClose": 15.5, "lastPrice": 78.3, "change": 62.8, "pChange": 405.16129032258067, "numberOfContractsTraded": 2575914, "totalTurnover": 111337.44, "nse_identifier": "OPTIDXNIFTY06-03-2025PE22000.00", "Support": "21922.8", "Resistance": null}, {"01.03.2025": "Put22200", "instrumentType": "Index Options", "expiryDate": "06-Mar-2025", "optionType": "Put", "strikePrice": 22200, "openPrice": 42.5, "highPrice": 180, "lowPrice": 42.5, "closePrice": 153.25, "prevClose": 32.5, "lastPrice": 153.2, "change": 120.69999999999999, "pChange": 371.38461538461536, "numberOfContractsTraded": 2317026, "totalTurnover": 197219.46, "nse_identifier": "OPTIDXNIFTY06-03-2025PE22200.00", "Support": "22046.75", "Resistance": null}, {"01.03.2025": "Put22300", "instrumentType": "Index Options", "expiryDate": "06-Mar-2025", "optionType": "Put", "strikePrice": 22300, "openPrice": 78.4, "highPrice": 239.4, "lowPrice": 71.5, "closePrice": 207.3, "prevClose": 49.15, "lastPrice": 210.65, "change": 161.5, "pChange": 328.5859613428281, "numberOfContractsTraded": 2195314, "totalTurnover": 233899.73, "nse_identifier": "OPTIDXNIFTY06-03-2025PE22300.00", "Support": "22092.7", "Resistance": null}, {"01.03.2025": "Call22300", "instrumentType": "Index Options", "expiryDate": "06-Mar-2025", "optionType": "Call", "strikePrice": 22300, "openPrice": 313.65, "highPrice": 313.65, "lowPrice": 82, "closePrice": 94.8, "prevClose": 346.05, "lastPrice": 89.05, "change": -257, "pChange": -74.26672446178297, "numberOfContractsTraded": 1995086, "totalTurnover": 188026.88, "nse_identifier": "OPTIDXNIFTY06-03-2025CE22300.00", "Support": null, "Resistance": "22394.8"}, {"01.03.2025": "Call22500", "instrumentType": "Index Options", "expiryDate": "06-Mar-2025", "optionType": "Call", "strikePrice": 22500, "openPrice": 145, "highPrice": 149, "lowPrice": 30.5, "closePrice": 35.7, "prevClose": 201.1, "lastPrice": 32.4, "change": -168.7, "pChange": -83.88861263053207, "numberOfContractsTraded": 1867659, "totalTurnover": 73216.9, "nse_identifier": "OPTIDXNIFTY06-03-2025CE22500.00", "Support": null, "Resistance": "22535.7"}, {"01.03.2025": "Put22100", "instrumentType": "Index Options", "expiryDate": "06-Mar-2025", "optionType": "Put", "strikePrice": 22100, "openPrice": 29, "highPrice": 131.4, "lowPrice": 29, "closePrice": 110.45, "prevClose": 22.65, "lastPrice": 110, "change": 87.35, "pChange": 385.6512141280353, "numberOfContractsTraded": 1734518, "totalTurnover": 118471.92, "nse_identifier": "OPTIDXNIFTY06-03-2025PE22100.00", "Support": "21989.55", "Resistance": null}, {"01.03.2025": "Put22250", "instrumentType": "Index Options", "expiryDate": "06-Mar-2025", "optionType": "Put", "strikePrice": 22250, "openPrice": 60.5, "highPrice": 208, "lowPrice": 60.5, "closePrice": 179.6, "prevClose": 40.05, "lastPrice": 180.2, "change": 140.14999999999998, "pChange": 349.93757802746563, "numberOfContractsTraded": 1482903, "totalTurnover": 135674.5, "nse_identifier": "OPTIDXNIFTY06-03-2025PE22250.00", "Support": "22070.4", "Resistance": null}, {"01.03.2025": "Call22600", "instrumentType": "Index Options", "expiryDate": "06-Mar-2025", "optionType": "Call", "strikePrice": 22600, "openPrice": 99, "highPrice": 99, "lowPrice": 18.15, "closePrice": 20.75, "prevClose": 141.2, "lastPrice": 18.6, "change": -122.6, "pChange": -86.8271954674221, "numberOfContractsTraded": 1474102, "totalTurnover": 35411.62, "nse_identifier": "OPTIDXNIFTY06-03-2025CE22600.00", "Support": null, "Resistance": "22620.75"}, {"01.03.2025": "Call22400", "instrumentType": "Index Options", "expiryDate": "06-Mar-2025", "optionType": "Call", "strikePrice": 22400, "openPrice": 200, "highPrice": 205.95, "lowPrice": 51.3, "closePrice": 59.65, "prevClose": 268.8, "lastPrice": 55, "change": -213.8, "pChange": -79.53869047619048, "numberOfContractsTraded": 1432735, "totalTurnover": 93174.34, "nse_identifier": "OPTIDXNIFTY06-03-2025CE22400.00", "Support": null, "Resistance": "22459.65"}, {"01.03.2025": "Put21800", "instrumentType": "Index Options", "expiryDate": "06-Mar-2025", "optionType": "Put", "strikePrice": 21800, "openPrice": 15, "highPrice": 42.45, "lowPrice": 6.15, "closePrice": 34.4, "prevClose": 7.6, "lastPrice": 35.1, "change": 27.5, "pChange": 361.8421052631579, "numberOfContractsTraded": 1363726, "totalTurnover": 28433.69, "nse_identifier": "OPTIDXNIFTY06-03-2025PE21800.00", "Support": "21765.6", "Resistance": null}, {"01.03.2025": "Put22150", "instrumentType": "Index Options", "expiryDate": "06-Mar-2025", "optionType": "Put", "strikePrice": 22150, "openPrice": 52, "highPrice": 154.25, "lowPrice": 44.35, "closePrice": 130.85, "prevClose": 27.15, "lastPrice": 131.1, "change": 103.94999999999999, "pChange": 382.87292817679554, "numberOfContractsTraded": 1286124, "totalTurnover": 104108.52, "nse_identifier": "OPTIDXNIFTY06-03-2025PE22150.00", "Support": "22019.15", "Resistance": null}, {"01.03.2025": "Call22700", "instrumentType": "Index Options", "expiryDate": "06-Mar-2025", "optionType": "Call", "strikePrice": 22700, "openPrice": 59, "highPrice": 63.75, "lowPrice": 10.6, "closePrice": 12.1, "prevClose": 93.4, "lastPrice": 11.1, "change": -82.30000000000001, "pChange": -88.11563169164883, "numberOfContractsTraded": 1271771, "totalTurnover": 18771.34, "nse_identifier": "OPTIDXNIFTY06-03-2025CE22700.00", "Support": null, "Resistance": "22712.1"}, {"01.03.2025": "Call22200", "instrumentType": "Index Options", "expiryDate": "06-Mar-2025", "optionType": "Call", "strikePrice": 22200, "openPrice": 399.65, "highPrice": 399.65, "lowPrice": 123.15, "closePrice": 140, "prevClose": 432.65, "lastPrice": 133.9, "change": -298.75, "pChange": -69.05119611695366, "numberOfContractsTraded": 1157050, "totalTurnover": 140651, "nse_identifier": "OPTIDXNIFTY06-03-2025CE22200.00", "Support": null, "Resistance": "22340"}, {"01.03.2025": "Put21900", "instrumentType": "Index Options", "expiryDate": "06-Mar-2025", "optionType": "Put", "strikePrice": 21900, "openPrice": 11.65, "highPrice": 63.4, "lowPrice": 11.65, "closePrice": 52.2, "prevClose": 10.6, "lastPrice": 51.65, "change": 41.05, "pChange": 387.2641509433962, "numberOfContractsTraded": 1073848, "totalTurnover": 30580.51, "nse_identifier": "OPTIDXNIFTY06-03-2025PE21900.00", "Support": "21847.8", "Resistance": null}, {"01.03.2025": "Call22800", "instrumentType": "Index Options", "expiryDate": "06-Mar-2025", "optionType": "Call", "strikePrice": 22800, "openPrice": 28.85, "highPrice": 42, "lowPrice": 6.5, "closePrice": 7.3, "prevClose": 56.85, "lastPrice": 6.7, "change": -50.15, "pChange": -88.2145998240985, "numberOfContractsTraded": 966837, "totalTurnover": 8338.97, "nse_identifier": "OPTIDXNIFTY06-03-2025CE22800.00", "Support": null, "Resistance": "22807.3"}, {"01.03.2025": "Call23000", "instrumentType": "Index Options", "expiryDate": "06-Mar-2025", "optionType": "Call", "strikePrice": 23000, "openPrice": 12, "highPrice": 12, "lowPrice": 3.05, "closePrice": 3.4, "prevClose": 17.3, "lastPrice": 3.1, "change": -14.200000000000001, "pChange": -82.08092485549133, "numberOfContractsTraded": 947816, "totalTurnover": 3234.42, "nse_identifier": "OPTIDXNIFTY06-03-2025CE23000.00", "Support": null, "Resistance": "23003.4"}, {"01.03.2025": "Call22350", "instrumentType": "Index Options", "expiryDate": "06-Mar-2025", "optionType": "Call", "strikePrice": 22350, "openPrice": 220, "highPrice": 227, "lowPrice": 65.25, "closePrice": 75.7, "prevClose": 306.1, "lastPrice": 70.5, "change": -235.60000000000002, "pChange": -76.96831100947404, "numberOfContractsTraded": 947311, "totalTurnover": 75723.3, "nse_identifier": "OPTIDXNIFTY06-03-2025CE22350.00", "Support": null, "Resistance": "22425.7"}, {"01.03.2025": "Call22250", "instrumentType": "Index Options", "expiryDate": "06-Mar-2025", "optionType": "Call", "strikePrice": 22250, "openPrice": 321, "highPrice": 321, "lowPrice": 101.15, "closePrice": 116, "prevClose": 387.6, "lastPrice": 110.55, "change": -277.05, "pChange": -71.47832817337462, "numberOfContractsTraded": 929108, "totalTurnover": 102225.11, "nse_identifier": "OPTIDXNIFTY06-03-2025CE22250.00", "Support": null, "Resistance": "22366"}, {"01.03.2025": "Put22400", "instrumentType": "Index Options", "expiryDate": "06-Mar-2025", "optionType": "Put", "strikePrice": 22400, "openPrice": 113.9, "highPrice": 309, "lowPrice": 105.55, "closePrice": 273.05, "prevClose": 71.5, "lastPrice": 278.35, "change": 206.85000000000002, "pChange": 289.3006993006993, "numberOfContractsTraded": 909097, "totalTurnover": 128823.59, "nse_identifier": "OPTIDXNIFTY06-03-2025PE22400.00", "Support": "22126.95", "Resistance": null}, {"01.03.2025": "Put21500", "instrumentType": "Index Options", "expiryDate": "06-Mar-2025", "optionType": "Put", "strikePrice": 21500, "openPrice": 5.1, "highPrice": 13.8, "lowPrice": 4.55, "closePrice": 10.8, "prevClose": 3.95, "lastPrice": 11, "change": 7.05, "pChange": 178.48101265822785, "numberOfContractsTraded": 908887, "totalTurnover": 6073.64, "nse_identifier": "OPTIDXNIFTY06-03-2025PE21500.00", "Support": "21489.2", "Resistance": null}, {"01.03.2025": "Put22050", "instrumentType": "Index Options", "expiryDate": "06-Mar-2025", "optionType": "Put", "strikePrice": 22050, "openPrice": 30.6, "highPrice": 110.5, "lowPrice": 28.9, "closePrice": 92.75, "prevClose": 18.25, "lastPrice": 93.8, "change": 75.55, "pChange": 413.972602739726, "numberOfContractsTraded": 843658, "totalTurnover": 46626.87, "nse_identifier": "OPTIDXNIFTY06-03-2025PE22050.00", "Support": "21957.25", "Resistance": null}, {"01.03.2025": "Put20800", "instrumentType": "Index Options", "expiryDate": "06-Mar-2025", "optionType": "Put", "strikePrice": 20800, "openPrice": 1.6, "highPrice": 2.9, "lowPrice": 1.25, "closePrice": 1.55, "prevClose": 1.7, "lastPrice": 1.8, "change": 0.10000000000000009, "pChange": 5.882352941176476, "numberOfContractsTraded": 821148, "totalTurnover": 1096.23, "nse_identifier": "OPTIDXNIFTY06-03-2025PE20800.00", "Support": "20798.45", "Resistance": null}, {"01.03.2025": "Put21700", "instrumentType": "Index Options", "expiryDate": "06-Mar-2025", "optionType": "Put", "strikePrice": 21700, "openPrice": 10.85, "highPrice": 28.7, "lowPrice": 5.75, "closePrice": 22.75, "prevClose": 5.75, "lastPrice": 22.6, "change": 16.85, "pChange": 293.0434782608696, "numberOfContractsTraded": 818259, "totalTurnover": 10905.35, "nse_identifier": "OPTIDXNIFTY06-03-2025PE21700.00", "Support": "21677.25", "Resistance": null}, {"01.03.2025": "Call22550", "instrumentType": "Index Options", "expiryDate": "06-Mar-2025", "optionType": "Call", "strikePrice": 22550, "openPrice": 124.2, "highPrice": 143, "lowPrice": 23.55, "closePrice": 27.4, "prevClose": 169.5, "lastPrice": 25.35, "change": -144.15, "pChange": -85.04424778761063, "numberOfContractsTraded": 809452, "totalTurnover": 23670.4, "nse_identifier": "OPTIDXNIFTY06-03-2025CE22550.00", "Support": null, "Resistance": "22577.4"}, {"01.03.2025": "Put22350", "instrumentType": "Index Options", "expiryDate": "06-Mar-2025", "optionType": "Put", "strikePrice": 22350, "openPrice": 79.75, "highPrice": 273.5, "lowPrice": 79.75, "closePrice": 239, "prevClose": 59.5, "lastPrice": 240, "change": 180.5, "pChange": 303.3613445378151, "numberOfContractsTraded": 781730, "totalTurnover": 93209.58, "nse_identifier": "OPTIDXNIFTY06-03-2025PE22350.00", "Support": "22111", "Resistance": null}, {"01.03.2025": "Call22900", "instrumentType": "Index Options", "expiryDate": "06-Mar-2025", "optionType": "Call", "strikePrice": 22900, "openPrice": 27, "highPrice": 27, "lowPrice": 4.15, "closePrice": 4.65, "prevClose": 32.35, "lastPrice": 4.15, "change": -28.200000000000003, "pChange": -87.17156105100464, "numberOfContractsTraded": 766671, "totalTurnover": 4099.77, "nse_identifier": "OPTIDXNIFTY06-03-2025CE22900.00", "Support": null, "Resistance": "22904.65"}, {"01.03.2025": "Call22450", "instrumentType": "Index Options", "expiryDate": "06-Mar-2025", "optionType": "Call", "strikePrice": 22450, "openPrice": 184.2, "highPrice": 184.2, "lowPrice": 39.65, "closePrice": 46.3, "prevClose": 233.1, "lastPrice": 42.25, "change": -190.85, "pChange": -81.87473187473188, "numberOfContractsTraded": 722283, "totalTurnover": 37302.31, "nse_identifier": "OPTIDXNIFTY06-03-2025CE22450.00", "Support": null, "Resistance": "22496.3"}, {"01.03.2025": "Call22650", "instrumentType": "Index Options", "expiryDate": "06-Mar-2025", "optionType": "Call", "strikePrice": 22650, "openPrice": 84.2, "highPrice": 84.2, "lowPrice": 13.7, "closePrice": 15.6, "prevClose": 115.9, "lastPrice": 14.5, "change": -101.4, "pChange": -87.48921484037963, "numberOfContractsTraded": 713863, "totalTurnover": 12994.09, "nse_identifier": "OPTIDXNIFTY06-03-2025CE22650.00", "Support": null, "Resistance": "22665.6"}, {"01.03.2025": "Put21950", "instrumentType": "Index Options", "expiryDate": "06-Mar-2025", "optionType": "Put", "strikePrice": 21950, "openPrice": 20, "highPrice": 77, "lowPrice": 18.85, "closePrice": 63.45, "prevClose": 12.7, "lastPrice": 64.65, "change": 51.95, "pChange": 409.0551181102363, "numberOfContractsTraded": 677918, "totalTurnover": 23566.12, "nse_identifier": "OPTIDXNIFTY06-03-2025PE21950.00", "Support": "21886.55", "Resistance": null}, {"01.03.2025": "Call23200", "instrumentType": "Index Options", "expiryDate": "06-Mar-2025", "optionType": "Call", "strikePrice": 23200, "openPrice": 3.35, "highPrice": 4.3, "lowPrice": 1.85, "closePrice": 2.1, "prevClose": 4.85, "lastPrice": 2.15, "change": -2.6999999999999997, "pChange": -55.670103092783506, "numberOfContractsTraded": 654394, "totalTurnover": 1212.26, "nse_identifier": "OPTIDXNIFTY06-03-2025CE23200.00", "Support": null, "Resistance": "23202.1"}, {"01.03.2025": "Call23500", "instrumentType": "Index Options", "expiryDate": "06-Mar-2025", "optionType": "Call", "strikePrice": 23500, "openPrice": 2, "highPrice": 2.4, "lowPrice": 1.3, "closePrice": 1.35, "prevClose": 1.95, "lastPrice": 1.35, "change": -0.5999999999999999, "pChange": -30.769230769230766, "numberOfContractsTraded": 626052, "totalTurnover": 737.18, "nse_identifier": "OPTIDXNIFTY06-03-2025CE23500.00", "Support": null, "Resistance": "23501.35"}, {"01.03.2025": "Put21600", "instrumentType": "Index Options", "expiryDate": "06-Mar-2025", "optionType": "Put", "strikePrice": 21600, "openPrice": 5.8, "highPrice": 19.45, "lowPrice": 5.2, "closePrice": 15.15, "prevClose": 4.75, "lastPrice": 14.95, "change": 10.2, "pChange": 214.73684210526315, "numberOfContractsTraded": 621761, "totalTurnover": 5679.79, "nse_identifier": "OPTIDXNIFTY06-03-2025PE21600.00", "Support": "21584.85", "Resistance": null}, {"01.03.2025": "Call22750", "instrumentType": "Index Options", "expiryDate": "06-Mar-2025", "optionType": "Call", "strikePrice": 22750, "openPrice": 49.2, "highPrice": 50, "lowPrice": 8.25, "closePrice": 9.25, "prevClose": 72.65, "lastPrice": 8.4, "change": -64.25, "pChange": -88.43771507226428, "numberOfContractsTraded": 609689, "totalTurnover": 6424.6, "nse_identifier": "OPTIDXNIFTY06-03-2025CE22750.00", "Support": null, "Resistance": "22759.25"}, {"01.03.2025": "Put21000", "instrumentType": "Index Options", "expiryDate": "06-Mar-2025", "optionType": "Put", "strikePrice": 21000, "openPrice": 2.2, "highPrice": 3.75, "lowPrice": 1.9, "closePrice": 2.9, "prevClose": 2.1, "lastPrice": 3.2, "change": 1.1, "pChange": 52.38095238095239, "numberOfContractsTraded": 594967, "totalTurnover": 1218.19, "nse_identifier": "OPTIDXNIFTY06-03-2025PE21000.00", "Support": "20997.1", "Resistance": null}, {"01.03.2025": "Call24000", "instrumentType": "Index Options", "expiryDate": "06-Mar-2025", "optionType": "Call", "strikePrice": 24000, "openPrice": 1.35, "highPrice": 1.55, "lowPrice": 0.95, "closePrice": 1.1, "prevClose": 1.35, "lastPrice": 1, "change": -0.3500000000000001, "pChange": -25.92592592592593, "numberOfContractsTraded": 576689, "totalTurnover": 519.02, "nse_identifier": "OPTIDXNIFTY06-03-2025CE24000.00", "Support": null, "Resistance": "24001.1"}, {"01.03.2025": "Put21850", "instrumentType": "Index Options", "expiryDate": "06-Mar-2025", "optionType": "Put", "strikePrice": 21850, "openPrice": 16.25, "highPrice": 52, "lowPrice": 13.4, "closePrice": 42.45, "prevClose": 9.05, "lastPrice": 42, "change": 32.95, "pChange": 364.08839779005524, "numberOfContractsTraded": 564936, "totalTurnover": 13274.58, "nse_identifier": "OPTIDXNIFTY06-03-2025PE21850.00", "Support": "21807.55", "Resistance": null}, {"01.03.2025": "Call23100", "instrumentType": "Index Options", "expiryDate": "06-Mar-2025", "optionType": "Call", "strikePrice": 23100, "openPrice": 7.15, "highPrice": 7.4, "lowPrice": 2.25, "closePrice": 2.5, "prevClose": 8.65, "lastPrice": 2.4, "change": -6.25, "pChange": -72.2543352601156, "numberOfContractsTraded": 559001, "totalTurnover": 1333.22, "nse_identifier": "OPTIDXNIFTY06-03-2025CE23100.00", "Support": null, "Resistance": "23102.5"}, {"01.03.2025": "Call22150", "instrumentType": "Index Options", "expiryDate": "06-Mar-2025", "optionType": "Call", "strikePrice": 22150, "openPrice": 371, "highPrice": 371, "lowPrice": 147.3, "closePrice": 167.05, "prevClose": 467.9, "lastPrice": 161.9, "change": -306, "pChange": -65.39858944218851, "numberOfContractsTraded": 519817, "totalTurnover": 67703.57, "nse_identifier": "OPTIDXNIFTY06-03-2025CE22150.00", "Support": null, "Resistance": "22317.05"}, {"01.03.2025": "Put21750", "instrumentType": "Index Options", "expiryDate": "06-Mar-2025", "optionType": "Put", "strikePrice": 21750, "openPrice": 10, "highPrice": 34.9, "lowPrice": 7.5, "closePrice": 27.9, "prevClose": 6.4, "lastPrice": 28, "change": 21.6, "pChange": 337.5, "numberOfContractsTraded": 498835, "totalTurnover": 8103.57, "nse_identifier": "OPTIDXNIFTY06-03-2025PE21750.00", "Support": "21722.1", "Resistance": null}, {"01.03.2025": "Call25500", "instrumentType": "Index Options", "expiryDate": "06-Mar-2025", "optionType": "Call", "strikePrice": 25500, "openPrice": 0.9, "highPrice": 1.2, "lowPrice": 0.85, "closePrice": 1, "prevClose": 1.05, "lastPrice": 0.95, "change": -0.10000000000000009, "pChange": -9.52380952380953, "numberOfContractsTraded": 492815, "totalTurnover": 362.22, "nse_identifier": "OPTIDXNIFTY06-03-2025CE25500.00", "Support": null, "Resistance": "25501"}, {"01.03.2025": "Put21300", "instrumentType": "Index Options", "expiryDate": "06-Mar-2025", "optionType": "Put", "strikePrice": 21300, "openPrice": 3.25, "highPrice": 7.45, "lowPrice": 3.05, "closePrice": 5.7, "prevClose": 2.85, "lastPrice": 6.3, "change": 3.4499999999999997, "pChange": 121.05263157894734, "numberOfContractsTraded": 488261, "totalTurnover": 1841.96, "nse_identifier": "OPTIDXNIFTY06-03-2025PE21300.00", "Support": "21294.3", "Resistance": null}, {"01.03.2025": "Call22100", "instrumentType": "Index Options", "expiryDate": "06-Mar-2025", "optionType": "Call", "strikePrice": 22100, "openPrice": 414.95, "highPrice": 420.75, "lowPrice": 174.35, "closePrice": 196.75, "prevClose": 521.2, "lastPrice": 190.8, "change": -330.40000000000003, "pChange": -63.39217191097467, "numberOfContractsTraded": 476430, "totalTurnover": 73472.65, "nse_identifier": "OPTIDXNIFTY06-03-2025CE22100.00", "Support": null, "Resistance": "22296.75"}, {"01.03.2025": "Call22850", "instrumentType": "Index Options", "expiryDate": "06-Mar-2025", "optionType": "Call", "strikePrice": 22850, "openPrice": 35, "highPrice": 35, "lowPrice": 5.25, "closePrice": 5.9, "prevClose": 43.45, "lastPrice": 5.5, "change": -37.95, "pChange": -87.34177215189874, "numberOfContractsTraded": 473035, "totalTurnover": 3068.81, "nse_identifier": "OPTIDXNIFTY06-03-2025CE22850.00", "Support": null, "Resistance": "22855.9"}, {"01.03.2025": "Put22500", "instrumentType": "Index Options", "expiryDate": "06-Mar-2025", "optionType": "Put", "strikePrice": 22500, "openPrice": 200, "highPrice": 388.4, "lowPrice": 142, "closePrice": 348.65, "prevClose": 102.7, "lastPrice": 355.75, "change": 253.05, "pChange": 246.3972736124635, "numberOfContractsTraded": 472919, "totalTurnover": 89214.99, "nse_identifier": "OPTIDXNIFTY06-03-2025PE22500.00", "Support": "22151.35", "Resistance": null}, {"01.03.2025": "Call23300", "instrumentType": "Index Options", "expiryDate": "06-Mar-2025", "optionType": "Call", "strikePrice": 23300, "openPrice": 3.1, "highPrice": 3.1, "lowPrice": 1.55, "closePrice": 1.7, "prevClose": 3.2, "lastPrice": 1.65, "change": -1.5500000000000003, "pChange": -48.43750000000001, "numberOfContractsTraded": 467786, "totalTurnover": 701.68, "nse_identifier": "OPTIDXNIFTY06-03-2025CE23300.00", "Support": null, "Resistance": "23301.7"}, {"01.03.2025": "Put21650", "instrumentType": "Index Options", "expiryDate": "06-Mar-2025", "optionType": "Put", "strikePrice": 21650, "openPrice": 5.2, "highPrice": 23.6, "lowPrice": 5.15, "closePrice": 18.45, "prevClose": 5.1, "lastPrice": 18.9, "change": 13.799999999999999, "pChange": 270.5882352941177, "numberOfContractsTraded": 412697, "totalTurnover": 4534.51, "nse_identifier": "OPTIDXNIFTY06-03-2025PE21650.00", "Support": "21631.55", "Resistance": null}, {"01.03.2025": "Put21400", "instrumentType": "Index Options", "expiryDate": "06-Mar-2025", "optionType": "Put", "strikePrice": 21400, "openPrice": 3.9, "highPrice": 9.85, "lowPrice": 3.55, "closePrice": 7.6, "prevClose": 3.2, "lastPrice": 8, "change": 4.8, "pChange": 149.99999999999997, "numberOfContractsTraded": 396135, "totalTurnover": 1957.9, "nse_identifier": "OPTIDXNIFTY06-03-2025PE21400.00", "Support": "21392.4", "Resistance": null}, {"01.03.2025": "Put21200", "instrumentType": "Index Options", "expiryDate": "06-Mar-2025", "optionType": "Put", "strikePrice": 21200, "openPrice": 3, "highPrice": 5.7, "lowPrice": 2.6, "closePrice": 4.5, "prevClose": 2.6, "lastPrice": 4.65, "change": 2.0500000000000003, "pChange": 78.84615384615385, "numberOfContractsTraded": 381266, "totalTurnover": 1149.52, "nse_identifier": "OPTIDXNIFTY06-03-2025PE21200.00", "Support": "21195.5", "Resistance": null}, {"01.03.2025": "Call22950", "instrumentType": "Index Options", "expiryDate": "06-Mar-2025", "optionType": "Call", "strikePrice": 22950, "openPrice": 19.65, "highPrice": 19.65, "lowPrice": 3.5, "closePrice": 3.95, "prevClose": 23.8, "lastPrice": 3.8, "change": -20, "pChange": -84.03361344537815, "numberOfContractsTraded": 349882, "totalTurnover": 1469.5, "nse_identifier": "OPTIDXNIFTY06-03-2025CE22950.00", "Support": null, "Resistance": "22953.95"}, {"01.03.2025": "Put21100", "instrumentType": "Index Options", "expiryDate": "06-Mar-2025", "optionType": "Put", "strikePrice": 21100, "openPrice": 2.9, "highPrice": 4.6, "lowPrice": 2.2, "closePrice": 3.7, "prevClose": 2.35, "lastPrice": 4.1, "change": 1.7499999999999996, "pChange": 74.46808510638296, "numberOfContractsTraded": 338019, "totalTurnover": 879.69, "nse_identifier": "OPTIDXNIFTY06-03-2025PE21100.00", "Support": "21096.3", "Resistance": null}, {"01.03.2025": "Call23400", "instrumentType": "Index Options", "expiryDate": "06-Mar-2025", "optionType": "Call", "strikePrice": 23400, "openPrice": 2.8, "highPrice": 2.9, "lowPrice": 1.35, "closePrice": 1.5, "prevClose": 2.4, "lastPrice": 1.4, "change": -1, "pChange": -41.66666666666667, "numberOfContractsTraded": 330304, "totalTurnover": 433.52, "nse_identifier": "OPTIDXNIFTY06-03-2025CE23400.00", "Support": null, "Resistance": "23401.5"}, {"01.03.2025": "Call23050", "instrumentType": "Index Options", "expiryDate": "06-Mar-2025", "optionType": "Call", "strikePrice": 23050, "openPrice": 11.3, "highPrice": 11.3, "lowPrice": 2.6, "closePrice": 2.9, "prevClose": 12.5, "lastPrice": 2.7, "change": -9.8, "pChange": -78.4, "numberOfContractsTraded": 317864, "totalTurnover": 867.77, "nse_identifier": "OPTIDXNIFTY06-03-2025CE23050.00", "Support": null, "Resistance": "23052.9"}, {"01.03.2025": "Put21450", "instrumentType": "Index Options", "expiryDate": "06-Mar-2025", "optionType": "Put", "strikePrice": 21450, "openPrice": 4.5, "highPrice": 11.5, "lowPrice": 4, "closePrice": 8.9, "prevClose": 3.35, "lastPrice": 9.5, "change": 6.15, "pChange": 183.5820895522388, "numberOfContractsTraded": 300565, "totalTurnover": 1699.7, "nse_identifier": "OPTIDXNIFTY06-03-2025PE21450.00", "Support": "21441.1", "Resistance": null}, {"01.03.2025": "Put21550", "instrumentType": "Index Options", "expiryDate": "06-Mar-2025", "optionType": "Put", "strikePrice": 21550, "openPrice": 6.6, "highPrice": 16.3, "lowPrice": 4.85, "closePrice": 12.65, "prevClose": 4.25, "lastPrice": 12.55, "change": 8.3, "pChange": 195.29411764705884, "numberOfContractsTraded": 292535, "totalTurnover": 2248.86, "nse_identifier": "OPTIDXNIFTY06-03-2025PE21550.00", "Support": "21537.35", "Resistance": null}, {"01.03.2025": "Put22450", "instrumentType": "Index Options", "expiryDate": "06-Mar-2025", "optionType": "Put", "strikePrice": 22450, "openPrice": 110, "highPrice": 347.1, "lowPrice": 109.95, "closePrice": 310.7, "prevClose": 86.2, "lastPrice": 312.05, "change": 225.85000000000002, "pChange": 262.00696055684455, "numberOfContractsTraded": 249797, "totalTurnover": 39204.39, "nse_identifier": "OPTIDXNIFTY06-03-2025PE22450.00", "Support": "22139.3", "Resistance": null}, {"01.03.2025": "Call23150", "instrumentType": "Index Options", "expiryDate": "06-Mar-2025", "optionType": "Call", "strikePrice": 23150, "openPrice": 6, "highPrice": 6, "lowPrice": 2.05, "closePrice": 2.2, "prevClose": 6.5, "lastPrice": 2.05, "change": -4.45, "pChange": -68.46153846153847, "numberOfContractsTraded": 246820, "totalTurnover": 505.36, "nse_identifier": "OPTIDXNIFTY06-03-2025CE23150.00", "Support": null, "Resistance": "23152.2"}, {"01.03.2025": "Call23600", "instrumentType": "Index Options", "expiryDate": "06-Mar-2025", "optionType": "Call", "strikePrice": 23600, "openPrice": 1.5, "highPrice": 1.85, "lowPrice": 1.15, "closePrice": 1.3, "prevClose": 1.7, "lastPrice": 1.45, "change": -0.25, "pChange": -14.705882352941178, "numberOfContractsTraded": 228436, "totalTurnover": 238.14, "nse_identifier": "OPTIDXNIFTY06-03-2025CE23600.00", "Support": null, "Resistance": "23601.3"}, {"01.03.2025": "Call22000", "instrumentType": "Index Options", "expiryDate": "06-Mar-2025", "optionType": "Call", "strikePrice": 22000, "openPrice": 521.1, "highPrice": 521.1, "lowPrice": 236, "closePrice": 262.7, "prevClose": 613.05, "lastPrice": 254.1, "change": -358.94999999999993, "pChange": -58.55150477122583, "numberOfContractsTraded": 216608, "totalTurnover": 47005.02, "nse_identifier": "OPTIDXNIFTY06-03-2025CE22000.00", "Support": null, "Resistance": "22262.7"}, {"01.03.2025": "Put21350", "instrumentType": "Index Options", "expiryDate": "06-Mar-2025", "optionType": "Put", "strikePrice": 21350, "openPrice": 3.75, "highPrice": 8.55, "lowPrice": 3.3, "closePrice": 6.5, "prevClose": 2.95, "lastPrice": 6.5, "change": 3.55, "pChange": 120.33898305084745, "numberOfContractsTraded": 213431, "totalTurnover": 933.23, "nse_identifier": "OPTIDXNIFTY06-03-2025PE21350.00", "Support": "21343.5", "Resistance": null}, {"01.03.2025": "Call24500", "instrumentType": "Index Options", "expiryDate": "06-Mar-2025", "optionType": "Call", "strikePrice": 24500, "openPrice": 1.2, "highPrice": 1.35, "lowPrice": 0.9, "closePrice": 1.05, "prevClose": 1.2, "lastPrice": 1, "change": -0.19999999999999996, "pChange": -16.666666666666664, "numberOfContractsTraded": 209219, "totalTurnover": 167.9, "nse_identifier": "OPTIDXNIFTY06-03-2025CE24500.00", "Support": null, "Resistance": "24501.05"}, {"01.03.2025": "Call23800", "instrumentType": "Index Options", "expiryDate": "06-Mar-2025", "optionType": "Call", "strikePrice": 23800, "openPrice": 1.45, "highPrice": 1.65, "lowPrice": 1.05, "closePrice": 1.2, "prevClose": 1.45, "lastPrice": 1.1, "change": -0.34999999999999987, "pChange": -24.13793103448275, "numberOfContractsTraded": 199063, "totalTurnover": 188.11, "nse_identifier": "OPTIDXNIFTY06-03-2025CE23800.00", "Support": null, "Resistance": "23801.2"}, {"01.03.2025": "Call23250", "instrumentType": "Index Options", "expiryDate": "06-Mar-2025", "optionType": "Call", "strikePrice": 23250, "openPrice": 3.75, "highPrice": 3.75, "lowPrice": 1.6, "closePrice": 1.9, "prevClose": 3.85, "lastPrice": 1.65, "change": -2.2, "pChange": -57.14285714285715, "numberOfContractsTraded": 190700, "totalTurnover": 321.81, "nse_identifier": "OPTIDXNIFTY06-03-2025CE23250.00", "Support": null, "Resistance": "23251.9"}, {"01.03.2025": "Put21250", "instrumentType": "Index Options", "expiryDate": "06-Mar-2025", "optionType": "Put", "strikePrice": 21250, "openPrice": 2.95, "highPrice": 6.45, "lowPrice": 2.75, "closePrice": 5, "prevClose": 2.65, "lastPrice": 5.45, "change": 2.8000000000000003, "pChange": 105.66037735849059, "numberOfContractsTraded": 189208, "totalTurnover": 632.9, "nse_identifier": "OPTIDXNIFTY06-03-2025PE21250.00", "Support": "21245", "Resistance": null}, {"01.03.2025": "Put20900", "instrumentType": "Index Options", "expiryDate": "06-Mar-2025", "optionType": "Put", "strikePrice": 20900, "openPrice": 3, "highPrice": 3.2, "lowPrice": 1.5, "closePrice": 2.05, "prevClose": 1.85, "lastPrice": 2, "change": 0.1499999999999999, "pChange": 8.108108108108103, "numberOfContractsTraded": 179211, "totalTurnover": 288.98, "nse_identifier": "OPTIDXNIFTY06-03-2025PE20900.00", "Support": "20897.95", "Resistance": null}, {"01.03.2025": "Call25000", "instrumentType": "Index Options", "expiryDate": "06-Mar-2025", "optionType": "Call", "strikePrice": 25000, "openPrice": 0.9, "highPrice": 1.3, "lowPrice": 0.85, "closePrice": 1, "prevClose": 1.1, "lastPrice": 1, "change": -0.10000000000000009, "pChange": -9.090909090909099, "numberOfContractsTraded": 176297, "totalTurnover": 134.87, "nse_identifier": "OPTIDXNIFTY06-03-2025CE25000.00", "Support": null, "Resistance": "25001"}, {"01.03.2025": "Put21150", "instrumentType": "Index Options", "expiryDate": "06-Mar-2025", "optionType": "Put", "strikePrice": 21150, "openPrice": 1.75, "highPrice": 5, "lowPrice": 1.75, "closePrice": 4, "prevClose": 2.45, "lastPrice": 4.5, "change": 2.05, "pChange": 83.67346938775509, "numberOfContractsTraded": 167557, "totalTurnover": 473.77, "nse_identifier": "OPTIDXNIFTY06-03-2025PE21150.00", "Support": "21146", "Resistance": null}, {"01.03.2025": "Call23700", "instrumentType": "Index Options", "expiryDate": "06-Mar-2025", "optionType": "Call", "strikePrice": 23700, "openPrice": 1.45, "highPrice": 1.6, "lowPrice": 1.1, "closePrice": 1.25, "prevClose": 1.45, "lastPrice": 1.2, "change": -0.25, "pChange": -17.24137931034483, "numberOfContractsTraded": 160823, "totalTurnover": 159.21, "nse_identifier": "OPTIDXNIFTY06-03-2025CE23700.00", "Support": null, "Resistance": "23701.25"}, {"01.03.2025": "Put22600", "instrumentType": "Index Options", "expiryDate": "06-Mar-2025", "optionType": "Put", "strikePrice": 22600, "openPrice": 225, "highPrice": 475, "lowPrice": 194.45, "closePrice": 432.4, "prevClose": 142.25, "lastPrice": 438, "change": 295.75, "pChange": 207.90861159929702, "numberOfContractsTraded": 149830, "totalTurnover": 36507.58, "nse_identifier": "OPTIDXNIFTY06-03-2025PE22600.00", "Support": "22167.6", "Resistance": null}, {"01.03.2025": "Put20850", "instrumentType": "Index Options", "expiryDate": "06-Mar-2025", "optionType": "Put", "strikePrice": 20850, "openPrice": 1.5, "highPrice": 3.2, "lowPrice": 1.3, "closePrice": 1.8, "prevClose": 1.75, "lastPrice": 1.9, "change": 0.1499999999999999, "pChange": 8.571428571428566, "numberOfContractsTraded": 147242, "totalTurnover": 215.34, "nse_identifier": "OPTIDXNIFTY06-03-2025PE20850.00", "Support": "20848.2", "Resistance": null}, {"01.03.2025": "Call23350", "instrumentType": "Index Options", "expiryDate": "06-Mar-2025", "optionType": "Call", "strikePrice": 23350, "openPrice": 2.8, "highPrice": 3.35, "lowPrice": 1.4, "closePrice": 1.6, "prevClose": 2.6, "lastPrice": 1.6, "change": -1, "pChange": -38.46153846153846, "numberOfContractsTraded": 140329, "totalTurnover": 196.81, "nse_identifier": "OPTIDXNIFTY06-03-2025CE23350.00", "Support": null, "Resistance": "23351.6"}, {"01.03.2025": "Call23900", "instrumentType": "Index Options", "expiryDate": "06-Mar-2025", "optionType": "Call", "strikePrice": 23900, "openPrice": 1.35, "highPrice": 1.65, "lowPrice": 1, "closePrice": 1.2, "prevClose": 1.35, "lastPrice": 1.15, "change": -0.20000000000000018, "pChange": -14.814814814814827, "numberOfContractsTraded": 131484, "totalTurnover": 117.35, "nse_identifier": "OPTIDXNIFTY06-03-2025CE23900.00", "Support": null, "Resistance": "23901.2"}, {"01.03.2025": "Put21050", "instrumentType": "Index Options", "expiryDate": "06-Mar-2025", "optionType": "Put", "strikePrice": 21050, "openPrice": 2.45, "highPrice": 5.9, "lowPrice": 2.05, "closePrice": 3.3, "prevClose": 2.15, "lastPrice": 3.1, "change": 0.9500000000000002, "pChange": 44.18604651162792, "numberOfContractsTraded": 101415, "totalTurnover": 225.14, "nse_identifier": "OPTIDXNIFTY06-03-2025PE21050.00", "Support": "21046.7", "Resistance": null}, {"01.03.2025": "Call23450", "instrumentType": "Index Options", "expiryDate": "06-Mar-2025", "optionType": "Call", "strikePrice": 23450, "openPrice": 2.6, "highPrice": 3, "lowPrice": 1.3, "closePrice": 1.4, "prevClose": 2.15, "lastPrice": 1.35, "change": -0.7999999999999998, "pChange": -37.20930232558139, "numberOfContractsTraded": 100854, "totalTurnover": 124.05, "nse_identifier": "OPTIDXNIFTY06-03-2025CE23450.00", "Support": null, "Resistance": "23451.4"}, {"01.03.2025": "Put22550", "instrumentType": "Index Options", "expiryDate": "06-Mar-2025", "optionType": "Put", "strikePrice": 22550, "openPrice": 140.05, "highPrice": 430, "lowPrice": 140.05, "closePrice": 392.95, "prevClose": 121.05, "lastPrice": 394.3, "change": 273.25, "pChange": 225.73316811235026, "numberOfContractsTraded": 86753, "totalTurnover": 17758.12, "nse_identifier": "OPTIDXNIFTY06-03-2025PE22550.00", "Support": "22157.05", "Resistance": null}, {"01.03.2025": "Put20950", "instrumentType": "Index Options", "expiryDate": "06-Mar-2025", "optionType": "Put", "strikePrice": 20950, "openPrice": 3.05, "highPrice": 3.35, "lowPrice": 1.65, "closePrice": 2.5, "prevClose": 1.9, "lastPrice": 2.05, "change": 0.1499999999999999, "pChange": 7.894736842105258, "numberOfContractsTraded": 82458, "totalTurnover": 150.9, "nse_identifier": "OPTIDXNIFTY06-03-2025PE20950.00", "Support": "20947.5", "Resistance": null}, {"01.03.2025": "Call24800", "instrumentType": "Index Options", "expiryDate": "06-Mar-2025", "optionType": "Call", "strikePrice": 24800, "openPrice": 1, "highPrice": 1.5, "lowPrice": 0.9, "closePrice": 1.05, "prevClose": 1, "lastPrice": 1, "change": 0, "pChange": 0, "numberOfContractsTraded": 74462, "totalTurnover": 61.43, "nse_identifier": "OPTIDXNIFTY06-03-2025CE24800.00", "Support": null, "Resistance": "24801.05"}, {"01.03.2025": "Call24100", "instrumentType": "Index Options", "expiryDate": "06-Mar-2025", "optionType": "Call", "strikePrice": 24100, "openPrice": 1.45, "highPrice": 1.6, "lowPrice": 0.95, "closePrice": 1.1, "prevClose": 1.25, "lastPrice": 1.25, "change": 0, "pChange": 0, "numberOfContractsTraded": 72512, "totalTurnover": 63.09, "nse_identifier": "OPTIDXNIFTY06-03-2025CE24100.00", "Support": null, "Resistance": "24101.1"}, {"01.03.2025": "Call22050", "instrumentType": "Index Options", "expiryDate": "06-Mar-2025", "optionType": "Call", "strikePrice": 22050, "openPrice": 427.2, "highPrice": 427.2, "lowPrice": 203.45, "closePrice": 228.05, "prevClose": 564.35, "lastPrice": 220.5, "change": -343.85, "pChange": -60.92850181624878, "numberOfContractsTraded": 71548, "totalTurnover": 12752, "nse_identifier": "OPTIDXNIFTY06-03-2025CE22050.00", "Support": null, "Resistance": "22278.05"}, {"01.03.2025": "Call23650", "instrumentType": "Index Options", "expiryDate": "06-Mar-2025", "optionType": "Call", "strikePrice": 23650, "openPrice": 1.9, "highPrice": 1.9, "lowPrice": 1.15, "closePrice": 1.25, "prevClose": 1.6, "lastPrice": 1.25, "change": -0.3500000000000001, "pChange": -21.875000000000007, "numberOfContractsTraded": 69387, "totalTurnover": 71.3, "nse_identifier": "OPTIDXNIFTY06-03-2025CE23650.00", "Support": null, "Resistance": "23651.25"}, {"01.03.2025": "Call25450", "instrumentType": "Index Options", "expiryDate": "06-Mar-2025", "optionType": "Call", "strikePrice": 25450, "openPrice": 1.1, "highPrice": 1.25, "lowPrice": 0.85, "closePrice": 1, "prevClose": 1.1, "lastPrice": 1, "change": -0.10000000000000009, "pChange": -9.090909090909099, "numberOfContractsTraded": 65032, "totalTurnover": 47.8, "nse_identifier": "OPTIDXNIFTY06-03-2025CE25450.00", "Support": null, "Resistance": "25451"}, {"01.03.2025": "Call23550", "instrumentType": "Index Options", "expiryDate": "06-Mar-2025", "optionType": "Call", "strikePrice": 23550, "openPrice": 1.75, "highPrice": 2.1, "lowPrice": 1.25, "closePrice": 1.35, "prevClose": 1.8, "lastPrice": 1.3, "change": -0.5, "pChange": -27.77777777777778, "numberOfContractsTraded": 63351, "totalTurnover": 69.84, "nse_identifier": "OPTIDXNIFTY06-03-2025CE23550.00", "Support": null, "Resistance": "23551.35"}, {"01.03.2025": "Call24200", "instrumentType": "Index Options", "expiryDate": "06-Mar-2025", "optionType": "Call", "strikePrice": 24200, "openPrice": 1.3, "highPrice": 1.45, "lowPrice": 0.95, "closePrice": 1.15, "prevClose": 1.3, "lastPrice": 1.1, "change": -0.19999999999999996, "pChange": -15.38461538461538, "numberOfContractsTraded": 60603, "totalTurnover": 52.72, "nse_identifier": "OPTIDXNIFTY06-03-2025CE24200.00", "Support": null, "Resistance": "24201.15"}, {"01.03.2025": "Put22700", "instrumentType": "Index Options", "expiryDate": "06-Mar-2025", "optionType": "Put", "strikePrice": 22700, "openPrice": 227, "highPrice": 569.9, "lowPrice": 227, "closePrice": 525.1, "prevClose": 194.4, "lastPrice": 528.45, "change": 334.05000000000007, "pChange": 171.83641975308646, "numberOfContractsTraded": 59088, "totalTurnover": 18530.29, "nse_identifier": "OPTIDXNIFTY06-03-2025PE22700.00", "Support": "22174.9", "Resistance": null}, {"01.03.2025": "Call23850", "instrumentType": "Index Options", "expiryDate": "06-Mar-2025", "optionType": "Call", "strikePrice": 23850, "openPrice": 1.3, "highPrice": 1.65, "lowPrice": 1.05, "closePrice": 1.2, "prevClose": 1.45, "lastPrice": 1.2, "change": -0.25, "pChange": -17.24137931034483, "numberOfContractsTraded": 58139, "totalTurnover": 54.07, "nse_identifier": "OPTIDXNIFTY06-03-2025CE23850.00", "Support": null, "Resistance": "23851.2"}, {"01.03.2025": "Call23750", "instrumentType": "Index Options", "expiryDate": "06-Mar-2025", "optionType": "Call", "strikePrice": 23750, "openPrice": 2.15, "highPrice": 2.15, "lowPrice": 1.1, "closePrice": 1.2, "prevClose": 1.5, "lastPrice": 1.2, "change": -0.30000000000000004, "pChange": -20.000000000000004, "numberOfContractsTraded": 54547, "totalTurnover": 53.18, "nse_identifier": "OPTIDXNIFTY06-03-2025CE23750.00", "Support": null, "Resistance": "23751.2"}, {"01.03.2025": "Call23950", "instrumentType": "Index Options", "expiryDate": "06-Mar-2025", "optionType": "Call", "strikePrice": 23950, "openPrice": 1, "highPrice": 6.45, "lowPrice": 1, "closePrice": 1.1, "prevClose": 1.3, "lastPrice": 1.1, "change": -0.19999999999999996, "pChange": -15.38461538461538, "numberOfContractsTraded": 50264, "totalTurnover": 44.86, "nse_identifier": "OPTIDXNIFTY06-03-2025CE23950.00", "Support": null, "Resistance": "23951.1"}, {"01.03.2025": "Call25400", "instrumentType": "Index Options", "expiryDate": "06-Mar-2025", "optionType": "Call", "strikePrice": 25400, "openPrice": 1, "highPrice": 1.25, "lowPrice": 0.85, "closePrice": 1, "prevClose": 1.05, "lastPrice": 0.95, "change": -0.10000000000000009, "pChange": -9.52380952380953, "numberOfContractsTraded": 47413, "totalTurnover": 35.2, "nse_identifier": "OPTIDXNIFTY06-03-2025CE25400.00", "Support": null, "Resistance": "25401"}, {"01.03.2025": "Call24600", "instrumentType": "Index Options", "expiryDate": "06-Mar-2025", "optionType": "Call", "strikePrice": 24600, "openPrice": 1.1, "highPrice": 1.4, "lowPrice": 0.95, "closePrice": 1.1, "prevClose": 1.1, "lastPrice": 1.05, "change": -0.050000000000000044, "pChange": -4.545454545454549, "numberOfContractsTraded": 46231, "totalTurnover": 39.18, "nse_identifier": "OPTIDXNIFTY06-03-2025CE24600.00", "Support": null, "Resistance": "24601.1"}, {"01.03.2025": "Call24700", "instrumentType": "Index Options", "expiryDate": "06-Mar-2025", "optionType": "Call", "strikePrice": 24700, "openPrice": 1.05, "highPrice": 1.35, "lowPrice": 0.9, "closePrice": 1.05, "prevClose": 1.05, "lastPrice": 1, "change": -0.050000000000000044, "pChange": -4.761904761904765, "numberOfContractsTraded": 46137, "totalTurnover": 38.06, "nse_identifier": "OPTIDXNIFTY06-03-2025CE24700.00", "Support": null, "Resistance": "24701.05"}, {"01.03.2025": "Call24300", "instrumentType": "Index Options", "expiryDate": "06-Mar-2025", "optionType": "Call", "strikePrice": 24300, "openPrice": 1.45, "highPrice": 1.5, "lowPrice": 0.95, "closePrice": 1.1, "prevClose": 1.25, "lastPrice": 1, "change": -0.25, "pChange": -20, "numberOfContractsTraded": 42943, "totalTurnover": 36.72, "nse_identifier": "OPTIDXNIFTY06-03-2025CE24300.00", "Support": null, "Resistance": "24301.1"}, {"01.03.2025": "Call24150", "instrumentType": "Index Options", "expiryDate": "06-Mar-2025", "optionType": "Call", "strikePrice": 24150, "openPrice": 1.25, "highPrice": 1.4, "lowPrice": 0.95, "closePrice": 1.1, "prevClose": 1.3, "lastPrice": 1, "change": -0.30000000000000004, "pChange": -23.076923076923077, "numberOfContractsTraded": 41342, "totalTurnover": 35.35, "nse_identifier": "OPTIDXNIFTY06-03-2025CE24150.00", "Support": null, "Resistance": "24151.1"}, {"01.03.2025": "Call25300", "instrumentType": "Index Options", "expiryDate": "06-Mar-2025", "optionType": "Call", "strikePrice": 25300, "openPrice": 1.6, "highPrice": 1.6, "lowPrice": 0.85, "closePrice": 1, "prevClose": 1.1, "lastPrice": 0.95, "change": -0.15000000000000013, "pChange": -13.636363636363647, "numberOfContractsTraded": 40613, "totalTurnover": 31.98, "nse_identifier": "OPTIDXNIFTY06-03-2025CE25300.00", "Support": null, "Resistance": "25301"}, {"01.03.2025": "Call24750", "instrumentType": "Index Options", "expiryDate": "06-Mar-2025", "optionType": "Call", "strikePrice": 24750, "openPrice": 1, "highPrice": 1.3, "lowPrice": 0.9, "closePrice": 1.05, "prevClose": 1, "lastPrice": 1.05, "change": 0.050000000000000044, "pChange": 5.000000000000004, "numberOfContractsTraded": 39213, "totalTurnover": 31.47, "nse_identifier": "OPTIDXNIFTY06-03-2025CE24750.00", "Support": null, "Resistance": "24751.05"}, {"01.03.2025": "Call24050", "instrumentType": "Index Options", "expiryDate": "06-Mar-2025", "optionType": "Call", "strikePrice": 24050, "openPrice": 1.25, "highPrice": 1.4, "lowPrice": 1, "closePrice": 1.1, "prevClose": 1.3, "lastPrice": 1.05, "change": -0.25, "pChange": -19.23076923076923, "numberOfContractsTraded": 38370, "totalTurnover": 33.38, "nse_identifier": "OPTIDXNIFTY06-03-2025CE24050.00", "Support": null, "Resistance": "24051.1"}, {"01.03.2025": "Put22800", "instrumentType": "Index Options", "expiryDate": "06-Mar-2025", "optionType": "Put", "strikePrice": 22800, "openPrice": 326, "highPrice": 661.55, "lowPrice": 326, "closePrice": 619.15, "prevClose": 259.3, "lastPrice": 624.25, "change": 364.95, "pChange": 140.74431160817585, "numberOfContractsTraded": 37108, "totalTurnover": 14316.54, "nse_identifier": "OPTIDXNIFTY06-03-2025PE22800.00", "Support": "22180.85", "Resistance": null}, {"01.03.2025": "Call24400", "instrumentType": "Index Options", "expiryDate": "06-Mar-2025", "optionType": "Call", "strikePrice": 24400, "openPrice": 1.25, "highPrice": 2.45, "lowPrice": 0.95, "closePrice": 1.05, "prevClose": 1.15, "lastPrice": 1.1, "change": -0.04999999999999982, "pChange": -4.347826086956506, "numberOfContractsTraded": 34805, "totalTurnover": 28.98, "nse_identifier": "OPTIDXNIFTY06-03-2025CE24400.00", "Support": null, "Resistance": "24401.05"}, {"01.03.2025": "Call24900", "instrumentType": "Index Options", "expiryDate": "06-Mar-2025", "optionType": "Call", "strikePrice": 24900, "openPrice": 0.95, "highPrice": 1.4, "lowPrice": 0.9, "closePrice": 1.1, "prevClose": 1.1, "lastPrice": 1.05, "change": -0.050000000000000044, "pChange": -4.545454545454549, "numberOfContractsTraded": 31804, "totalTurnover": 26.24, "nse_identifier": "OPTIDXNIFTY06-03-2025CE24900.00", "Support": null, "Resistance": "24901.1"}, {"01.03.2025": "Put22650", "instrumentType": "Index Options", "expiryDate": "06-Mar-2025", "optionType": "Put", "strikePrice": 22650, "openPrice": 231.6, "highPrice": 521.1, "lowPrice": 222.6, "closePrice": 478, "prevClose": 167.25, "lastPrice": 484, "change": 316.75, "pChange": 189.38714499252615, "numberOfContractsTraded": 31635, "totalTurnover": 8373.47, "nse_identifier": "OPTIDXNIFTY06-03-2025PE22650.00", "Support": "22172", "Resistance": null}, {"01.03.2025": "Call25200", "instrumentType": "Index Options", "expiryDate": "06-Mar-2025", "optionType": "Call", "strikePrice": 25200, "openPrice": 1, "highPrice": 1.25, "lowPrice": 0.9, "closePrice": 1.05, "prevClose": 1.05, "lastPrice": 0.95, "change": -0.10000000000000009, "pChange": -9.52380952380953, "numberOfContractsTraded": 27483, "totalTurnover": 21.64, "nse_identifier": "OPTIDXNIFTY06-03-2025CE25200.00", "Support": null, "Resistance": "25201.05"}, {"01.03.2025": "Call24250", "instrumentType": "Index Options", "expiryDate": "06-Mar-2025", "optionType": "Call", "strikePrice": 24250, "openPrice": 1.2, "highPrice": 1.45, "lowPrice": 1, "closePrice": 1.15, "prevClose": 1.1, "lastPrice": 1.05, "change": -0.050000000000000044, "pChange": -4.545454545454549, "numberOfContractsTraded": 24364, "totalTurnover": 21.01, "nse_identifier": "OPTIDXNIFTY06-03-2025CE24250.00", "Support": null, "Resistance": "24251.15"}, {"01.03.2025": "Call24550", "instrumentType": "Index Options", "expiryDate": "06-Mar-2025", "optionType": "Call", "strikePrice": 24550, "openPrice": 1.05, "highPrice": 1.35, "lowPrice": 0.95, "closePrice": 1.05, "prevClose": 1.1, "lastPrice": 1, "change": -0.10000000000000009, "pChange": -9.090909090909099, "numberOfContractsTraded": 20648, "totalTurnover": 17.03, "nse_identifier": "OPTIDXNIFTY06-03-2025CE24550.00", "Support": null, "Resistance": "24551.05"}, {"01.03.2025": "Call25100", "instrumentType": "Index Options", "expiryDate": "06-Mar-2025", "optionType": "Call", "strikePrice": 25100, "openPrice": 0.95, "highPrice": 1.25, "lowPrice": 0.85, "closePrice": 1.05, "prevClose": 1.1, "lastPrice": 0.9, "change": -0.20000000000000007, "pChange": -18.181818181818183, "numberOfContractsTraded": 20580, "totalTurnover": 16.21, "nse_identifier": "OPTIDXNIFTY06-03-2025CE25100.00", "Support": null, "Resistance": "25101.05"}, {"01.03.2025": "Call25350", "instrumentType": "Index Options", "expiryDate": "06-Mar-2025", "optionType": "Call", "strikePrice": 25350, "openPrice": 1.3, "highPrice": 1.3, "lowPrice": 0.9, "closePrice": 1, "prevClose": 1.1, "lastPrice": 1, "change": -0.10000000000000009, "pChange": -9.090909090909099, "numberOfContractsTraded": 20068, "totalTurnover": 15.35, "nse_identifier": "OPTIDXNIFTY06-03-2025CE25350.00", "Support": null, "Resistance": "25351"}, {"01.03.2025": "Call21900", "instrumentType": "Index Options", "expiryDate": "06-Mar-2025", "optionType": "Call", "strikePrice": 21900, "openPrice": 650, "highPrice": 650, "lowPrice": 306.7, "closePrice": 338.35, "prevClose": 710.25, "lastPrice": 329.5, "change": -380.75, "pChange": -53.607884547694475, "numberOfContractsTraded": 19912, "totalTurnover": 5453.6, "nse_identifier": "OPTIDXNIFTY06-03-2025CE21900.00", "Support": null, "Resistance": "22238.35"}, {"01.03.2025": "Call25250", "instrumentType": "Index Options", "expiryDate": "06-Mar-2025", "optionType": "Call", "strikePrice": 25250, "openPrice": 1.5, "highPrice": 1.5, "lowPrice": 0.85, "closePrice": 1, "prevClose": 1.05, "lastPrice": 0.9, "change": -0.15000000000000002, "pChange": -14.285714285714288, "numberOfContractsTraded": 19054, "totalTurnover": 14.86, "nse_identifier": "OPTIDXNIFTY06-03-2025CE25250.00", "Support": null, "Resistance": "25251"}, {"01.03.2025": "Call25050", "instrumentType": "Index Options", "expiryDate": "06-Mar-2025", "optionType": "Call", "strikePrice": 25050, "openPrice": 0.9, "highPrice": 1.4, "lowPrice": 0.85, "closePrice": 1, "prevClose": 1.1, "lastPrice": 0.9, "change": -0.20000000000000007, "pChange": -18.181818181818183, "numberOfContractsTraded": 17977, "totalTurnover": 13.75, "nse_identifier": "OPTIDXNIFTY06-03-2025CE25050.00", "Support": null, "Resistance": "25051"}, {"01.03.2025": "Call24350", "instrumentType": "Index Options", "expiryDate": "06-Mar-2025", "optionType": "Call", "strikePrice": 24350, "openPrice": 1.35, "highPrice": 1.4, "lowPrice": 1, "closePrice": 1.1, "prevClose": 1.15, "lastPrice": 1.2, "change": 0.050000000000000044, "pChange": 4.347826086956526, "numberOfContractsTraded": 17608, "totalTurnover": 15.05, "nse_identifier": "OPTIDXNIFTY06-03-2025CE24350.00", "Support": null, "Resistance": "24351.1"}, {"01.03.2025": "Call24450", "instrumentType": "Index Options", "expiryDate": "06-Mar-2025", "optionType": "Call", "strikePrice": 24450, "openPrice": 1.15, "highPrice": 1.4, "lowPrice": 0.95, "closePrice": 1.1, "prevClose": 1.15, "lastPrice": 1, "change": -0.1499999999999999, "pChange": -13.04347826086956, "numberOfContractsTraded": 16040, "totalTurnover": 13.59, "nse_identifier": "OPTIDXNIFTY06-03-2025CE24450.00", "Support": null, "Resistance": "24451.1"}, {"01.03.2025": "Call24950", "instrumentType": "Index Options", "expiryDate": "06-Mar-2025", "optionType": "Call", "strikePrice": 24950, "openPrice": 1.1, "highPrice": 1.3, "lowPrice": 0.9, "closePrice": 1.05, "prevClose": 1.05, "lastPrice": 1, "change": -0.050000000000000044, "pChange": -4.761904761904765, "numberOfContractsTraded": 15917, "totalTurnover": 12.53, "nse_identifier": "OPTIDXNIFTY06-03-2025CE24950.00", "Support": null, "Resistance": "24951.05"}, {"01.03.2025": "Call21950", "instrumentType": "Index Options", "expiryDate": "06-Mar-2025", "optionType": "Call", "strikePrice": 21950, "openPrice": 486, "highPrice": 496, "lowPrice": 270, "closePrice": 299.6, "prevClose": 941, "lastPrice": 292.5, "change": -648.5, "pChange": -68.91604675876727, "numberOfContractsTraded": 15748, "totalTurnover": 3652.79, "nse_identifier": "OPTIDXNIFTY06-03-2025CE21950.00", "Support": null, "Resistance": "22249.6"}, {"01.03.2025": "Call21800", "instrumentType": "Index Options", "expiryDate": "06-Mar-2025", "optionType": "Call", "strikePrice": 21800, "openPrice": 621.05, "highPrice": 637.4, "lowPrice": 385.1, "closePrice": 418.4, "prevClose": 795.65, "lastPrice": 411.3, "change": -384.34999999999997, "pChange": -48.30641613774901, "numberOfContractsTraded": 15179, "totalTurnover": 5132.7, "nse_identifier": "OPTIDXNIFTY06-03-2025CE21800.00", "Support": null, "Resistance": "22218.4"}, {"01.03.2025": "Call24850", "instrumentType": "Index Options", "expiryDate": "06-Mar-2025", "optionType": "Call", "strikePrice": 24850, "openPrice": 0.95, "highPrice": 1.3, "lowPrice": 0.9, "closePrice": 1.05, "prevClose": 1.15, "lastPrice": 0.9, "change": -0.2499999999999999, "pChange": -21.7391304347826, "numberOfContractsTraded": 12920, "totalTurnover": 10.47, "nse_identifier": "OPTIDXNIFTY06-03-2025CE24850.00", "Support": null, "Resistance": "24851.05"}, {"01.03.2025": "Put23000", "instrumentType": "Index Options", "expiryDate": "06-Mar-2025", "optionType": "Put", "strikePrice": 23000, "openPrice": 508.9, "highPrice": 857.05, "lowPrice": 508.9, "closePrice": 815.7, "prevClose": 418.15, "lastPrice": 818.65, "change": 400.5, "pChange": 95.77902666507235, "numberOfContractsTraded": 11902, "totalTurnover": 6373.34, "nse_identifier": "OPTIDXNIFTY06-03-2025PE23000.00", "Support": "22184.3", "Resistance": null}, {"01.03.2025": "Call24650", "instrumentType": "Index Options", "expiryDate": "06-Mar-2025", "optionType": "Call", "strikePrice": 24650, "openPrice": 1.1, "highPrice": 1.95, "lowPrice": 0.95, "closePrice": 1.05, "prevClose": 1.05, "lastPrice": 1, "change": -0.050000000000000044, "pChange": -4.761904761904765, "numberOfContractsTraded": 10544, "totalTurnover": 8.62, "nse_identifier": "OPTIDXNIFTY06-03-2025CE24650.00", "Support": null, "Resistance": "24651.05"}, {"01.03.2025": "Put22900", "instrumentType": "Index Options", "expiryDate": "06-Mar-2025", "optionType": "Put", "strikePrice": 22900, "openPrice": 394, "highPrice": 755.95, "lowPrice": 394, "closePrice": 716.45, "prevClose": 333.15, "lastPrice": 720.05, "change": 386.9, "pChange": 116.13387363049677, "numberOfContractsTraded": 8080, "totalTurnover": 3622.37, "nse_identifier": "OPTIDXNIFTY06-03-2025PE22900.00", "Support": "22183.55", "Resistance": null}, {"01.03.2025": "Call25150", "instrumentType": "Index Options", "expiryDate": "06-Mar-2025", "optionType": "Call", "strikePrice": 25150, "openPrice": 1.05, "highPrice": 1.25, "lowPrice": 0.9, "closePrice": 1, "prevClose": 1.05, "lastPrice": 1.05, "change": 0, "pChange": 0, "numberOfContractsTraded": 7813, "totalTurnover": 6.09, "nse_identifier": "OPTIDXNIFTY06-03-2025CE25150.00", "Support": null, "Resistance": "25151"}, {"01.03.2025": "Put22750", "instrumentType": "Index Options", "expiryDate": "06-Mar-2025", "optionType": "Put", "strikePrice": 22750, "openPrice": 296, "highPrice": 613.2, "lowPrice": 281.05, "closePrice": 571.4, "prevClose": 223.95, "lastPrice": 577.45, "change": 353.50000000000006, "pChange": 157.84773386916726, "numberOfContractsTraded": 7634, "totalTurnover": 2518.88, "nse_identifier": "OPTIDXNIFTY06-03-2025PE22750.00", "Support": "22178.6", "Resistance": null}, {"01.03.2025": "Call21500", "instrumentType": "Index Options", "expiryDate": "06-Mar-2025", "optionType": "Call", "strikePrice": 21500, "openPrice": 925.6, "highPrice": 925.6, "lowPrice": 658.4, "closePrice": 694.5, "prevClose": 1098.55, "lastPrice": 690.45, "change": -408.0999999999999, "pChange": -37.14896909562604, "numberOfContractsTraded": 4373, "totalTurnover": 2416.03, "nse_identifier": "OPTIDXNIFTY06-03-2025CE21500.00", "Support": null, "Resistance": "22194.5"}, {"01.03.2025": "Put22850", "instrumentType": "Index Options", "expiryDate": "06-Mar-2025", "optionType": "Put", "strikePrice": 22850, "openPrice": 321, "highPrice": 708.3, "lowPrice": 321, "closePrice": 669.7, "prevClose": 296.2, "lastPrice": 672.65, "change": 376.45, "pChange": 127.09318028359218, "numberOfContractsTraded": 3485, "totalTurnover": 1331.97, "nse_identifier": "OPTIDXNIFTY06-03-2025PE22850.00", "Support": "22180.3", "Resistance": null}, {"01.03.2025": "Call21700", "instrumentType": "Index Options", "expiryDate": "06-Mar-2025", "optionType": "Call", "strikePrice": 21700, "openPrice": 715.95, "highPrice": 734.45, "lowPrice": 473.25, "closePrice": 507.5, "prevClose": 904.95, "lastPrice": 503.3, "change": -401.65000000000003, "pChange": -44.383667605945085, "numberOfContractsTraded": 3110, "totalTurnover": 1237.3, "nse_identifier": "OPTIDXNIFTY06-03-2025CE21700.00", "Support": null, "Resistance": "22207.5"}, {"01.03.2025": "Call21850", "instrumentType": "Index Options", "expiryDate": "06-Mar-2025", "optionType": "Call", "strikePrice": 21850, "openPrice": 581.2, "highPrice": 591.4, "lowPrice": 346.35, "closePrice": 377.85, "prevClose": 762, "lastPrice": 371.1, "change": -390.9, "pChange": -51.29921259842519, "numberOfContractsTraded": 2720, "totalTurnover": 812.94, "nse_identifier": "OPTIDXNIFTY06-03-2025CE21850.00", "Support": null, "Resistance": "22227.85"}, {"01.03.2025": "Put23100", "instrumentType": "Index Options", "expiryDate": "06-Mar-2025", "optionType": "Put", "strikePrice": 23100, "openPrice": 625.05, "highPrice": 950.15, "lowPrice": 625.05, "closePrice": 916.75, "prevClose": 505.35, "lastPrice": 920.95, "change": 415.6, "pChange": 82.2400316612249, "numberOfContractsTraded": 1617, "totalTurnover": 1012.95, "nse_identifier": "OPTIDXNIFTY06-03-2025PE23100.00", "Support": "22183.25", "Resistance": null}, {"01.03.2025": "Put23500", "instrumentType": "Index Options", "expiryDate": "06-Mar-2025", "optionType": "Put", "strikePrice": 23500, "openPrice": 1018.5, "highPrice": 1348.65, "lowPrice": 1018.5, "closePrice": 1310.55, "prevClose": 896.1, "lastPrice": 1322.2, "change": 426.1, "pChange": 47.55049659636201, "numberOfContractsTraded": 1048, "totalTurnover": 939.11, "nse_identifier": "OPTIDXNIFTY06-03-2025PE23500.00", "Support": "22189.45", "Resistance": null}, {"01.03.2025": "Call21750", "instrumentType": "Index Options", "expiryDate": "06-Mar-2025", "optionType": "Call", "strikePrice": 21750, "openPrice": 586.45, "highPrice": 603.4, "lowPrice": 428.75, "closePrice": 459.95, "prevClose": 859.1, "lastPrice": 454.95, "change": -404.15000000000003, "pChange": -47.04341752997323, "numberOfContractsTraded": 1024, "totalTurnover": 373.96, "nse_identifier": "OPTIDXNIFTY06-03-2025CE21750.00", "Support": null, "Resistance": "22209.95"}, {"01.03.2025": "Call21400", "instrumentType": "Index Options", "expiryDate": "06-Mar-2025", "optionType": "Call", "strikePrice": 21400, "openPrice": 956, "highPrice": 956, "lowPrice": 753.9, "closePrice": 792.95, "prevClose": 1188, "lastPrice": 786, "change": -402, "pChange": -33.83838383838384, "numberOfContractsTraded": 956, "totalTurnover": 569.69, "nse_identifier": "OPTIDXNIFTY06-03-2025CE21400.00", "Support": null, "Resistance": "22192.95"}, {"01.03.2025": "Put22950", "instrumentType": "Index Options", "expiryDate": "06-Mar-2025", "optionType": "Put", "strikePrice": 22950, "openPrice": 549.95, "highPrice": 808.05, "lowPrice": 533.65, "closePrice": 763.9, "prevClose": 376.35, "lastPrice": 770.1, "change": 393.75, "pChange": 104.6233559186927, "numberOfContractsTraded": 936, "totalTurnover": 446.74, "nse_identifier": "OPTIDXNIFTY06-03-2025PE22950.00", "Support": "22186.1", "Resistance": null}, {"01.03.2025": "Put23200", "instrumentType": "Index Options", "expiryDate": "06-Mar-2025", "optionType": "Put", "strikePrice": 23200, "openPrice": 740, "highPrice": 1050.05, "lowPrice": 740, "closePrice": 1016.7, "prevClose": 606, "lastPrice": 1019, "change": 413, "pChange": 68.15181518151815, "numberOfContractsTraded": 833, "totalTurnover": 552.41, "nse_identifier": "OPTIDXNIFTY06-03-2025PE23200.00", "Support": "22183.3", "Resistance": null}, {"01.03.2025": "Call21600", "instrumentType": "Index Options", "expiryDate": "06-Mar-2025", "optionType": "Call", "strikePrice": 21600, "openPrice": 820, "highPrice": 830.35, "lowPrice": 569, "closePrice": 602.35, "prevClose": 1003, "lastPrice": 594.2, "change": -408.79999999999995, "pChange": -40.757726819541375, "numberOfContractsTraded": 680, "totalTurnover": 318.66, "nse_identifier": "OPTIDXNIFTY06-03-2025CE21600.00", "Support": null, "Resistance": "22202.35"}, {"01.03.2025": "Call21000", "instrumentType": "Index Options", "expiryDate": "06-Mar-2025", "optionType": "Call", "strikePrice": 21000, "openPrice": 1290, "highPrice": 1359, "lowPrice": 1159.85, "closePrice": 1185.2, "prevClose": 1592.35, "lastPrice": 1177.2, "change": -415.14999999999986, "pChange": -26.071529500423896, "numberOfContractsTraded": 489, "totalTurnover": 454.36, "nse_identifier": "OPTIDXNIFTY06-03-2025CE21000.00", "Support": null, "Resistance": "22185.2"}, {"01.03.2025": "Put23050", "instrumentType": "Index Options", "expiryDate": "06-Mar-2025", "optionType": "Put", "strikePrice": 23050, "openPrice": 639, "highPrice": 905.55, "lowPrice": 629, "closePrice": 859.35, "prevClose": 462.9, "lastPrice": 867.3, "change": 404.4, "pChange": 87.36228127025275, "numberOfContractsTraded": 426, "totalTurnover": 230.4, "nse_identifier": "OPTIDXNIFTY06-03-2025PE23050.00", "Support": "22190.65", "Resistance": null}, {"01.03.2025": "Put24000", "instrumentType": "Index Options", "expiryDate": "06-Mar-2025", "optionType": "Put", "strikePrice": 24000, "openPrice": 1561, "highPrice": 1845, "lowPrice": 1561, "closePrice": 1813.2, "prevClose": 1395.4, "lastPrice": 1821.45, "change": 426.04999999999995, "pChange": 30.53246380966031, "numberOfContractsTraded": 378, "totalTurnover": 490.77, "nse_identifier": "OPTIDXNIFTY06-03-2025PE24000.00", "Support": "22186.8", "Resistance": null}, {"01.03.2025": "Put23300", "instrumentType": "Index Options", "expiryDate": "06-Mar-2025", "optionType": "Put", "strikePrice": 23300, "openPrice": 895.55, "highPrice": 1152.2, "lowPrice": 890.7, "closePrice": 1114.25, "prevClose": 697.1, "lastPrice": 1124.1, "change": 426.9999999999999, "pChange": 61.253765600344266, "numberOfContractsTraded": 362, "totalTurnover": 275.25, "nse_identifier": "OPTIDXNIFTY06-03-2025PE23300.00", "Support": "22185.75", "Resistance": null}, {"01.03.2025": "Put23150", "instrumentType": "Index Options", "expiryDate": "06-Mar-2025", "optionType": "Put", "strikePrice": 23150, "openPrice": 697.55, "highPrice": 988.65, "lowPrice": 697.55, "closePrice": 968.65, "prevClose": 565.6, "lastPrice": 969.35, "change": 403.75, "pChange": 71.38437057991513, "numberOfContractsTraded": 275, "totalTurnover": 170.17, "nse_identifier": "OPTIDXNIFTY06-03-2025PE23150.00", "Support": "22181.35", "Resistance": null}, {"01.03.2025": "Put23600", "instrumentType": "Index Options", "expiryDate": "06-Mar-2025", "optionType": "Put", "strikePrice": 23600, "openPrice": 1199.85, "highPrice": 1440, "lowPrice": 1190.4, "closePrice": 1420.15, "prevClose": 997, "lastPrice": 1417, "change": 420, "pChange": 42.126379137412236, "numberOfContractsTraded": 174, "totalTurnover": 169.43, "nse_identifier": "OPTIDXNIFTY06-03-2025PE23600.00", "Support": "22179.85", "Resistance": null}, {"01.03.2025": "Put23400", "instrumentType": "Index Options", "expiryDate": "06-Mar-2025", "optionType": "Put", "strikePrice": 23400, "openPrice": 982.95, "highPrice": 1245, "lowPrice": 982.9, "closePrice": 1209.05, "prevClose": 798.85, "lastPrice": 1209.05, "change": 410.19999999999993, "pChange": 51.34881392001, "numberOfContractsTraded": 141, "totalTurnover": 120.02, "nse_identifier": "OPTIDXNIFTY06-03-2025PE23400.00", "Support": "22190.95", "Resistance": null}, {"01.03.2025": "Call21300", "instrumentType": "Index Options", "expiryDate": "06-Mar-2025", "optionType": "Call", "strikePrice": 21300, "openPrice": 1120, "highPrice": 1120.05, "lowPrice": 866.95, "closePrice": 895.7, "prevClose": 1290, "lastPrice": 895, "change": -395, "pChange": -30.620155038759687, "numberOfContractsTraded": 100, "totalTurnover": 69.24, "nse_identifier": "OPTIDXNIFTY06-03-2025CE21300.00", "Support": null, "Resistance": "22195.7"}, {"01.03.2025": "Put23250", "instrumentType": "Index Options", "expiryDate": "06-Mar-2025", "optionType": "Put", "strikePrice": 23250, "openPrice": 849.6, "highPrice": 1097.95, "lowPrice": 824.15, "closePrice": 1063, "prevClose": 651.45, "lastPrice": 1063, "change": 411.54999999999995, "pChange": 63.17445698058177, "numberOfContractsTraded": 92, "totalTurnover": 64.44, "nse_identifier": "OPTIDXNIFTY06-03-2025PE23250.00", "Support": "22187", "Resistance": null}, {"01.03.2025": "Put23350", "instrumentType": "Index Options", "expiryDate": "06-Mar-2025", "optionType": "Put", "strikePrice": 23350, "openPrice": 917.85, "highPrice": 1181.45, "lowPrice": 917.85, "closePrice": 1139, "prevClose": 748.05, "lastPrice": 1139, "change": 390.95000000000005, "pChange": 52.262549294833235, "numberOfContractsTraded": 88, "totalTurnover": 72.87, "nse_identifier": "OPTIDXNIFTY06-03-2025PE23350.00", "Support": "22211", "Resistance": null}, {"01.03.2025": "Put23800", "instrumentType": "Index Options", "expiryDate": "06-Mar-2025", "optionType": "Put", "strikePrice": 23800, "openPrice": 1402.9, "highPrice": 1630, "lowPrice": 1385, "closePrice": 1610.5, "prevClose": 1192.1, "lastPrice": 1610, "change": 417.9000000000001, "pChange": 35.05578391074575, "numberOfContractsTraded": 73, "totalTurnover": 81.51, "nse_identifier": "OPTIDXNIFTY06-03-2025PE23800.00", "Support": "22189.5", "Resistance": null}, {"01.03.2025": "Put24500", "instrumentType": "Index Options", "expiryDate": "06-Mar-2025", "optionType": "Put", "strikePrice": 24500, "openPrice": 1925, "highPrice": 2341.25, "lowPrice": 1925, "closePrice": 2291.65, "prevClose": 1888.65, "lastPrice": 2291.65, "change": 403, "pChange": 21.337992746141424, "numberOfContractsTraded": 69, "totalTurnover": 116.16, "nse_identifier": "OPTIDXNIFTY06-03-2025PE24500.00", "Support": "22208.35", "Resistance": null}, {"01.03.2025": "Put25000", "instrumentType": "Index Options", "expiryDate": "06-Mar-2025", "optionType": "Put", "strikePrice": 25000, "openPrice": 2600, "highPrice": 2824, "lowPrice": 2592.1, "closePrice": 2810, "prevClose": 2389.8, "lastPrice": 2810, "change": 420.1999999999998, "pChange": 17.583061344045518, "numberOfContractsTraded": 63, "totalTurnover": 128.48, "nse_identifier": "OPTIDXNIFTY06-03-2025PE25000.00", "Support": "22190", "Resistance": null}, {"01.03.2025": "Put23700", "instrumentType": "Index Options", "expiryDate": "06-Mar-2025", "optionType": "Put", "strikePrice": 23700, "openPrice": 1365, "highPrice": 1551.95, "lowPrice": 1353.3, "closePrice": 1515.6, "prevClose": 1095.3, "lastPrice": 1511.2, "change": 415.9000000000001, "pChange": 37.97133205514472, "numberOfContractsTraded": 51, "totalTurnover": 54.64, "nse_identifier": "OPTIDXNIFTY06-03-2025PE23700.00", "Support": "22184.4", "Resistance": null}, {"01.03.2025": "Put24200", "instrumentType": "Index Options", "expiryDate": "06-Mar-2025", "optionType": "Put", "strikePrice": 24200, "openPrice": 1776.65, "highPrice": 2033, "lowPrice": 1776.65, "closePrice": 1978.25, "prevClose": 1598.7, "lastPrice": 1978.25, "change": 379.54999999999995, "pChange": 23.741164696315753, "numberOfContractsTraded": 34, "totalTurnover": 48.78, "nse_identifier": "OPTIDXNIFTY06-03-2025PE24200.00", "Support": "22221.75", "Resistance": null}, {"01.03.2025": "Put24700", "instrumentType": "Index Options", "expiryDate": "06-Mar-2025", "optionType": "Put", "strikePrice": 24700, "openPrice": 2238.8, "highPrice": 2410, "lowPrice": 2200, "closePrice": 2410, "prevClose": 2093.4, "lastPrice": 2410, "change": 316.5999999999999, "pChange": 15.12372217445304, "numberOfContractsTraded": 30, "totalTurnover": 51.48, "nse_identifier": "OPTIDXNIFTY06-03-2025PE24700.00", "Support": "22290", "Resistance": null}, {"01.03.2025": "Call21200", "instrumentType": "Index Options", "expiryDate": "06-Mar-2025", "optionType": "Call", "strikePrice": 21200, "openPrice": 968.25, "highPrice": 1104.6, "lowPrice": 959, "closePrice": 985.8, "prevClose": 1453.75, "lastPrice": 985, "change": -468.75, "pChange": -32.244196044711956, "numberOfContractsTraded": 24, "totalTurnover": 17.69, "nse_identifier": "OPTIDXNIFTY06-03-2025CE21200.00", "Support": null, "Resistance": "22185.8"}, {"01.03.2025": "Call21050", "instrumentType": "Index Options", "expiryDate": "06-Mar-2025", "optionType": "Call", "strikePrice": 21050, "openPrice": 1421.5, "highPrice": 1421.5, "lowPrice": 1115.4, "closePrice": 1140, "prevClose": 1598.05, "lastPrice": 1140, "change": -458.04999999999995, "pChange": -28.663058102061882, "numberOfContractsTraded": 21, "totalTurnover": 20.71, "nse_identifier": "OPTIDXNIFTY06-03-2025CE21050.00", "Support": null, "Resistance": "22190"}, {"01.03.2025": "Put23750", "instrumentType": "Index Options", "expiryDate": "06-Mar-2025", "optionType": "Put", "strikePrice": 23750, "openPrice": 1572.5, "highPrice": 1572.5, "lowPrice": 1530.2, "closePrice": 1572, "prevClose": 1145.15, "lastPrice": 1572, "change": 426.8499999999999, "pChange": 37.27459284809849, "numberOfContractsTraded": 18, "totalTurnover": 21.13, "nse_identifier": "OPTIDXNIFTY06-03-2025PE23750.00", "Support": "22178", "Resistance": null}, {"01.03.2025": "Put23900", "instrumentType": "Index Options", "expiryDate": "06-Mar-2025", "optionType": "Put", "strikePrice": 23900, "openPrice": 1580, "highPrice": 1623, "lowPrice": 1545, "closePrice": 1623, "prevClose": 1303.95, "lastPrice": 1623, "change": 319.04999999999995, "pChange": 24.467962728632227, "numberOfContractsTraded": 17, "totalTurnover": 20.19, "nse_identifier": "OPTIDXNIFTY06-03-2025PE23900.00", "Support": "22277", "Resistance": null}, {"01.03.2025": "Call21450", "instrumentType": "Index Options", "expiryDate": "06-Mar-2025", "optionType": "Call", "strikePrice": 21450, "openPrice": 992.1, "highPrice": 992.1, "lowPrice": 714.55, "closePrice": 772.85, "prevClose": 1210, "lastPrice": 772.85, "change": -437.15, "pChange": -36.12809917355372, "numberOfContractsTraded": 14, "totalTurnover": 8.12, "nse_identifier": "OPTIDXNIFTY06-03-2025CE21450.00", "Support": null, "Resistance": "22222.85"}, {"01.03.2025": "Put24300", "instrumentType": "Index Options", "expiryDate": "06-Mar-2025", "optionType": "Put", "strikePrice": 24300, "openPrice": 1912, "highPrice": 2133, "lowPrice": 1912, "closePrice": 2112.7, "prevClose": 1692.95, "lastPrice": 2108, "change": 415.04999999999995, "pChange": 24.51637673882867, "numberOfContractsTraded": 13, "totalTurnover": 19.58, "nse_identifier": "OPTIDXNIFTY06-03-2025PE24300.00", "Support": "22187.3", "Resistance": null}, {"01.03.2025": "Put24050", "instrumentType": "Index Options", "expiryDate": "06-Mar-2025", "optionType": "Put", "strikePrice": 24050, "openPrice": 1649, "highPrice": 1799.25, "lowPrice": 1649, "closePrice": 1798.95, "prevClose": 1446.6, "lastPrice": 1798.95, "change": 352.35000000000014, "pChange": 24.35711323102448, "numberOfContractsTraded": 13, "totalTurnover": 17.35, "nse_identifier": "OPTIDXNIFTY06-03-2025PE24050.00", "Support": "22251.05", "Resistance": null}, {"01.03.2025": "Put25200", "instrumentType": "Index Options", "expiryDate": "06-Mar-2025", "optionType": "Put", "strikePrice": 25200, "openPrice": 2728.95, "highPrice": 2983, "lowPrice": 2728.95, "closePrice": 2983, "prevClose": 2584.55, "lastPrice": 2983, "change": 398.4499999999998, "pChange": 15.41661024162813, "numberOfContractsTraded": 11, "totalTurnover": 23.07, "nse_identifier": "OPTIDXNIFTY06-03-2025PE25200.00", "Support": "22217", "Resistance": null}, {"01.03.2025": "Put24100", "instrumentType": "Index Options", "expiryDate": "06-Mar-2025", "optionType": "Put", "strikePrice": 24100, "openPrice": 1940, "highPrice": 1940, "lowPrice": 1892, "closePrice": 1914.5, "prevClose": 1497.35, "lastPrice": 1914.95, "change": 417.60000000000014, "pChange": 27.889271045513752, "numberOfContractsTraded": 8, "totalTurnover": 11.52, "nse_identifier": "OPTIDXNIFTY06-03-2025PE24100.00", "Support": "22185.5", "Resistance": null}, {"01.03.2025": "Put24600", "instrumentType": "Index Options", "expiryDate": "06-Mar-2025", "optionType": "Put", "strikePrice": 24600, "openPrice": 2100, "highPrice": 2270, "lowPrice": 2100, "closePrice": 2270, "prevClose": 1990.8, "lastPrice": 2270, "change": 279.20000000000005, "pChange": 14.024512758689978, "numberOfContractsTraded": 7, "totalTurnover": 11.38, "nse_identifier": "OPTIDXNIFTY06-03-2025PE24600.00", "Support": "22330", "Resistance": null}, {"01.03.2025": "Put25500", "instrumentType": "Index Options", "expiryDate": "06-Mar-2025", "optionType": "Put", "strikePrice": 25500, "openPrice": 3186.3, "highPrice": 3270.75, "lowPrice": 3186.3, "closePrice": 3270.75, "prevClose": 2895.15, "lastPrice": 3270.75, "change": 375.5999999999999, "pChange": 12.973421066265994, "numberOfContractsTraded": 5, "totalTurnover": 12.02, "nse_identifier": "OPTIDXNIFTY06-03-2025PE25500.00", "Support": "22229.25", "Resistance": null}, {"01.03.2025": "Put23850", "instrumentType": "Index Options", "expiryDate": "06-Mar-2025", "optionType": "Put", "strikePrice": 23850, "openPrice": 1550, "highPrice": 1550, "lowPrice": 1550, "closePrice": 1550, "prevClose": 1200.2, "lastPrice": 1550, "change": 349.79999999999995, "pChange": 29.145142476253955, "numberOfContractsTraded": 4, "totalTurnover": 4.65, "nse_identifier": "OPTIDXNIFTY06-03-2025PE23850.00", "Support": "22300", "Resistance": null}, {"01.03.2025": "Put25300", "instrumentType": "Index Options", "expiryDate": "06-Mar-2025", "optionType": "Put", "strikePrice": 25300, "openPrice": 2950, "highPrice": 2950, "lowPrice": 2950, "closePrice": 2950, "prevClose": 2700, "lastPrice": 2950, "change": 250, "pChange": 9.25925925925926, "numberOfContractsTraded": 3, "totalTurnover": 6.64, "nse_identifier": "OPTIDXNIFTY06-03-2025PE25300.00", "Support": "22350", "Resistance": null}, {"01.03.2025": "Put24250", "instrumentType": "Index Options", "expiryDate": "06-Mar-2025", "optionType": "Put", "strikePrice": 24250, "openPrice": 1965, "highPrice": 2025, "lowPrice": 1965, "closePrice": 2025, "prevClose": 1630.25, "lastPrice": 2025, "change": 394.75, "pChange": 24.21407759546082, "numberOfContractsTraded": 2, "totalTurnover": 2.99, "nse_identifier": "OPTIDXNIFTY06-03-2025PE24250.00", "Support": "22225", "Resistance": null}, {"01.03.2025": "Put24800", "instrumentType": "Index Options", "expiryDate": "06-Mar-2025", "optionType": "Put", "strikePrice": 24800, "openPrice": 2625, "highPrice": 2625, "lowPrice": 2625, "closePrice": 2625, "prevClose": 2197.95, "lastPrice": 2625, "change": 427.0500000000002, "pChange": 19.429468368252245, "numberOfContractsTraded": 2, "totalTurnover": 3.94, "nse_identifier": "OPTIDXNIFTY06-03-2025PE24800.00", "Support": "22175", "Resistance": null}, {"01.03.2025": "Put23450", "instrumentType": "Index Options", "expiryDate": "06-Mar-2025", "optionType": "Put", "strikePrice": 23450, "openPrice": 1047.1, "highPrice": 1285.2, "lowPrice": 1047.1, "closePrice": 1285.2, "prevClose": 845.1, "lastPrice": 1285.2, "change": 440.1, "pChange": 52.07667731629393, "numberOfContractsTraded": 2, "totalTurnover": 1.75, "nse_identifier": "OPTIDXNIFTY06-03-2025PE23450.00", "Support": "22164.8", "Resistance": null}, {"01.03.2025": "Put23650", "instrumentType": "Index Options", "expiryDate": "06-Mar-2025", "optionType": "Put", "strikePrice": 23650, "openPrice": 1302.4, "highPrice": 1469.4, "lowPrice": 1302.4, "closePrice": 1469.4, "prevClose": 990.3, "lastPrice": 1469.4, "change": 479.10000000000014, "pChange": 48.37927900636173, "numberOfContractsTraded": 2, "totalTurnover": 2.08, "nse_identifier": "OPTIDXNIFTY06-03-2025PE23650.00", "Support": "22180.6", "Resistance": null}, {"01.03.2025": "Put25100", "instrumentType": "Index Options", "expiryDate": "06-Mar-2025", "optionType": "Put", "strikePrice": 25100, "openPrice": 2925, "highPrice": 2925, "lowPrice": 2925, "closePrice": 2925, "prevClose": 2469.1, "lastPrice": 2925, "change": 455.9000000000001, "pChange": 18.464217731157106, "numberOfContractsTraded": 1, "totalTurnover": 2.19, "nse_identifier": "OPTIDXNIFTY06-03-2025PE25100.00", "Support": "22175", "Resistance": null}, {"01.03.2025": "Put24550", "instrumentType": "Index Options", "expiryDate": "06-Mar-2025", "optionType": "Put", "strikePrice": 24550, "openPrice": 2375, "highPrice": 2375, "lowPrice": 2375, "closePrice": 2375, "prevClose": 1880, "lastPrice": 2375, "change": 495, "pChange": 26.329787234042552, "numberOfContractsTraded": 1, "totalTurnover": 1.78, "nse_identifier": "OPTIDXNIFTY06-03-2025PE24550.00", "Support": "22175", "Resistance": null}, {"01.03.2025": "Call21150", "instrumentType": "Index Options", "expiryDate": "06-Mar-2025", "optionType": "Call", "strikePrice": 21150, "openPrice": 1185.6, "highPrice": 1185.6, "lowPrice": 1185.6, "closePrice": 1185.6, "prevClose": 1732.05, "lastPrice": 1185.6, "change": -546.45, "pChange": -31.549320169741062, "numberOfContractsTraded": 1, "totalTurnover": 0.89, "nse_identifier": "OPTIDXNIFTY06-03-2025CE21150.00", "Support": null, "Resistance": "22335.6"}, {"01.03.2025": "Put24350", "instrumentType": "Index Options", "expiryDate": "06-Mar-2025", "optionType": "Put", "strikePrice": 24350, "openPrice": 0, "highPrice": 0, "lowPrice": 0, "closePrice": 1749.5, "prevClose": 1749.5, "lastPrice": 1751, "change": 1.5, "pChange": 0.08573878250928837, "numberOfContractsTraded": 0, "totalTurnover": 0, "nse_identifier": "OPTIDXNIFTY06-03-2025PE24350.00", "Support": "22600.5", "Resistance": null}, {"01.03.2025": "Put23550", "instrumentType": "Index Options", "expiryDate": "06-Mar-2025", "optionType": "Put", "strikePrice": 23550, "openPrice": 0, "highPrice": 0, "lowPrice": 0, "closePrice": 619.85, "prevClose": 619.85, "lastPrice": 619.85, "change": 0, "pChange": 0, "numberOfContractsTraded": 0, "totalTurnover": 0, "nse_identifier": "OPTIDXNIFTY06-03-2025PE23550.00", "Support": "22930.15", "Resistance": null}, {"01.03.2025": "Call20850", "instrumentType": "Index Options", "expiryDate": "06-Mar-2025", "optionType": "Call", "strikePrice": 20850, "openPrice": 0, "highPrice": 0, "lowPrice": 0, "closePrice": 0, "prevClose": 2537.9, "lastPrice": 0, "change": 0, "pChange": 0, "numberOfContractsTraded": 0, "totalTurnover": 0, "nse_identifier": "OPTIDXNIFTY06-03-2025CE20850.00", "Support": null, "Resistance": "20850"}, {"01.03.2025": "Call20900", "instrumentType": "Index Options", "expiryDate": "06-Mar-2025", "optionType": "Call", "strikePrice": 20900, "openPrice": 0, "highPrice": 0, "lowPrice": 0, "closePrice": 0, "prevClose": 2489.35, "lastPrice": 0, "change": 0, "pChange": 0, "numberOfContractsTraded": 0, "totalTurnover": 0, "nse_identifier": "OPTIDXNIFTY06-03-2025CE20900.00", "Support": null, "Resistance": "20900"}, {"01.03.2025": "Call20800", "instrumentType": "Index Options", "expiryDate": "06-Mar-2025", "optionType": "Call", "strikePrice": 20800, "openPrice": 0, "highPrice": 0, "lowPrice": 0, "closePrice": 0, "prevClose": 1805, "lastPrice": 1805, "change": 0, "pChange": 0, "numberOfContractsTraded": 0, "totalTurnover": 0, "nse_identifier": "OPTIDXNIFTY06-03-2025CE20800.00", "Support": null, "Resistance": "20800"}, {"01.03.2025": "Call20950", "instrumentType": "Index Options", "expiryDate": "06-Mar-2025", "optionType": "Call", "strikePrice": 20950, "openPrice": 0, "highPrice": 0, "lowPrice": 0, "closePrice": 0, "prevClose": 2440.9, "lastPrice": 0, "change": 0, "pChange": 0, "numberOfContractsTraded": 0, "totalTurnover": 0, "nse_identifier": "OPTIDXNIFTY06-03-2025CE20950.00", "Support": null, "Resistance": "20950"}, {"01.03.2025": "Put24900", "instrumentType": "Index Options", "expiryDate": "06-Mar-2025", "optionType": "Put", "strikePrice": 24900, "openPrice": 0, "highPrice": 0, "lowPrice": 0, "closePrice": 2290, "prevClose": 2290, "lastPrice": 2290, "change": 0, "pChange": 0, "numberOfContractsTraded": 0, "totalTurnover": 0, "nse_identifier": "OPTIDXNIFTY06-03-2025PE24900.00", "Support": "22610", "Resistance": null}, {"01.03.2025": "Call21650", "instrumentType": "Index Options", "expiryDate": "06-Mar-2025", "optionType": "Call", "strikePrice": 21650, "openPrice": 0, "highPrice": 0, "lowPrice": 0, "closePrice": 1228.65, "prevClose": 1228.65, "lastPrice": 1228.65, "change": 0, "pChange": 0, "numberOfContractsTraded": 0, "totalTurnover": 0, "nse_identifier": "OPTIDXNIFTY06-03-2025CE21650.00", "Support": null, "Resistance": "22878.65"}, {"01.03.2025": "Put24650", "instrumentType": "Index Options", "expiryDate": "06-Mar-2025", "optionType": "Put", "strikePrice": 24650, "openPrice": 0, "highPrice": 0, "lowPrice": 0, "closePrice": 1763.1, "prevClose": 1763.1, "lastPrice": 1763.1, "change": 0, "pChange": 0, "numberOfContractsTraded": 0, "totalTurnover": 0, "nse_identifier": "OPTIDXNIFTY06-03-2025PE24650.00", "Support": "22886.9", "Resistance": null}, {"01.03.2025": "Put24950", "instrumentType": "Index Options", "expiryDate": "06-Mar-2025", "optionType": "Put", "strikePrice": 24950, "openPrice": 0, "highPrice": 0, "lowPrice": 0, "closePrice": 1857.55, "prevClose": 1857.55, "lastPrice": 1857.9, "change": 0.3500000000001364, "pChange": 0.018842023094944222, "numberOfContractsTraded": 0, "totalTurnover": 0, "nse_identifier": "OPTIDXNIFTY06-03-2025PE24950.00", "Support": "23092.45", "Resistance": null}, {"01.03.2025": "Put24850", "instrumentType": "Index Options", "expiryDate": "06-Mar-2025", "optionType": "Put", "strikePrice": 24850, "openPrice": 0, "highPrice": 0, "lowPrice": 0, "closePrice": 1969.55, "prevClose": 1969.55, "lastPrice": 1969.55, "change": 0, "pChange": 0, "numberOfContractsTraded": 0, "totalTurnover": 0, "nse_identifier": "OPTIDXNIFTY06-03-2025PE24850.00", "Support": "22880.45", "Resistance": null}, {"01.03.2025": "Put25350", "instrumentType": "Index Options", "expiryDate": "06-Mar-2025", "optionType": "Put", "strikePrice": 25350, "openPrice": 0, "highPrice": 0, "lowPrice": 0, "closePrice": 2460.15, "prevClose": 2460.15, "lastPrice": 2460.15, "change": 0, "pChange": 0, "numberOfContractsTraded": 0, "totalTurnover": 0, "nse_identifier": "OPTIDXNIFTY06-03-2025PE25350.00", "Support": "22889.85", "Resistance": null}, {"01.03.2025": "Put25450", "instrumentType": "Index Options", "expiryDate": "06-Mar-2025", "optionType": "Put", "strikePrice": 25450, "openPrice": 0, "highPrice": 0, "lowPrice": 0, "closePrice": 2558.4, "prevClose": 2558.4, "lastPrice": 2558.4, "change": 0, "pChange": 0, "numberOfContractsTraded": 0, "totalTurnover": 0, "nse_identifier": "OPTIDXNIFTY06-03-2025PE25450.00", "Support": "22891.6", "Resistance": null}, {"01.03.2025": "Put24400", "instrumentType": "Index Options", "expiryDate": "06-Mar-2025", "optionType": "Put", "strikePrice": 24400, "openPrice": 0, "highPrice": 0, "lowPrice": 0, "closePrice": 1799.25, "prevClose": 1799.25, "lastPrice": 1799.65, "change": 0.40000000000009095, "pChange": 0.022231485341119406, "numberOfContractsTraded": 0, "totalTurnover": 0, "nse_identifier": "OPTIDXNIFTY06-03-2025PE24400.00", "Support": "22600.75", "Resistance": null}, {"01.03.2025": "Put24150", "instrumentType": "Index Options", "expiryDate": "06-Mar-2025", "optionType": "Put", "strikePrice": 24150, "openPrice": 0, "highPrice": 0, "lowPrice": 0, "closePrice": 1488.05, "prevClose": 1488.05, "lastPrice": 1488.05, "change": 0, "pChange": 0, "numberOfContractsTraded": 0, "totalTurnover": 0, "nse_identifier": "OPTIDXNIFTY06-03-2025PE24150.00", "Support": "22661.95", "Resistance": null}, {"01.03.2025": "Put25250", "instrumentType": "Index Options", "expiryDate": "06-Mar-2025", "optionType": "Put", "strikePrice": 25250, "openPrice": 0, "highPrice": 0, "lowPrice": 0, "closePrice": 2356.8, "prevClose": 2356.8, "lastPrice": 2356.8, "change": 0, "pChange": 0, "numberOfContractsTraded": 0, "totalTurnover": 0, "nse_identifier": "OPTIDXNIFTY06-03-2025PE25250.00", "Support": "22893.2", "Resistance": null}, {"01.03.2025": "Put24450", "instrumentType": "Index Options", "expiryDate": "06-Mar-2025", "optionType": "Put", "strikePrice": 24450, "openPrice": 0, "highPrice": 0, "lowPrice": 0, "closePrice": 1785, "prevClose": 1785, "lastPrice": 1785, "change": 0, "pChange": 0, "numberOfContractsTraded": 0, "totalTurnover": 0, "nse_identifier": "OPTIDXNIFTY06-03-2025PE24450.00", "Support": "22665", "Resistance": null}, {"01.03.2025": "Put25150", "instrumentType": "Index Options", "expiryDate": "06-Mar-2025", "optionType": "Put", "strikePrice": 25150, "openPrice": 0, "highPrice": 0, "lowPrice": 0, "closePrice": 2268.3, "prevClose": 2268.3, "lastPrice": 2268.3, "change": 0, "pChange": 0, "numberOfContractsTraded": 0, "totalTurnover": 0, "nse_identifier": "OPTIDXNIFTY06-03-2025PE25150.00", "Support": "22881.7", "Resistance": null}, {"01.03.2025": "Call21550", "instrumentType": "Index Options", "expiryDate": "06-Mar-2025", "optionType": "Call", "strikePrice": 21550, "openPrice": 0, "highPrice": 0, "lowPrice": 0, "closePrice": 1112.75, "prevClose": 1112.75, "lastPrice": 1112.7, "change": -0.049999999999954525, "pChange": -0.004493372275888971, "numberOfContractsTraded": 0, "totalTurnover": 0, "nse_identifier": "OPTIDXNIFTY06-03-2025CE21550.00", "Support": null, "Resistance": "22662.75"}, {"01.03.2025": "Call21250", "instrumentType": "Index Options", "expiryDate": "06-Mar-2025", "optionType": "Call", "strikePrice": 21250, "openPrice": 0, "highPrice": 0, "lowPrice": 0, "closePrice": 1630.3, "prevClose": 1630.3, "lastPrice": 1630.3, "change": 0, "pChange": 0, "numberOfContractsTraded": 0, "totalTurnover": 0, "nse_identifier": "OPTIDXNIFTY06-03-2025CE21250.00", "Support": null, "Resistance": "22880.3"}, {"01.03.2025": "Put25050", "instrumentType": "Index Options", "expiryDate": "06-Mar-2025", "optionType": "Put", "strikePrice": 25050, "openPrice": 0, "highPrice": 0, "lowPrice": 0, "closePrice": 2159.9, "prevClose": 2159.9, "lastPrice": 2159.9, "change": 0, "pChange": 0, "numberOfContractsTraded": 0, "totalTurnover": 0, "nse_identifier": "OPTIDXNIFTY06-03-2025PE25050.00", "Support": "22890.1", "Resistance": null}, {"01.03.2025": "Put25400", "instrumentType": "Index Options", "expiryDate": "06-Mar-2025", "optionType": "Put", "strikePrice": 25400, "openPrice": 0, "highPrice": 0, "lowPrice": 0, "closePrice": 2781, "prevClose": 2781, "lastPrice": 2781, "change": 0, "pChange": 0, "numberOfContractsTraded": 0, "totalTurnover": 0, "nse_identifier": "OPTIDXNIFTY06-03-2025PE25400.00", "Support": "22619", "Resistance": null}, {"01.03.2025": "Call21100", "instrumentType": "Index Options", "expiryDate": "06-Mar-2025", "optionType": "Call", "strikePrice": 21100, "openPrice": 0, "highPrice": 0, "lowPrice": 0, "closePrice": 1774.1, "prevClose": 1774.1, "lastPrice": 1774.1, "change": 0, "pChange": 0, "numberOfContractsTraded": 0, "totalTurnover": 0, "nse_identifier": "OPTIDXNIFTY06-03-2025CE21100.00", "Support": null, "Resistance": "22874.1"}, {"01.03.2025": "Put23950", "instrumentType": "Index Options", "expiryDate": "06-Mar-2025", "optionType": "Put", "strikePrice": 23950, "openPrice": 0, "highPrice": 0, "lowPrice": 0, "closePrice": 1333, "prevClose": 1333, "lastPrice": 1333, "change": 0, "pChange": 0, "numberOfContractsTraded": 0, "totalTurnover": 0, "nse_identifier": "OPTIDXNIFTY06-03-2025PE23950.00", "Support": "22617", "Resistance": null}, {"01.03.2025": "Call21350", "instrumentType": "Index Options", "expiryDate": "06-Mar-2025", "optionType": "Call", "strikePrice": 21350, "openPrice": 0, "highPrice": 0, "lowPrice": 0, "closePrice": 1530.95, "prevClose": 1530.95, "lastPrice": 1530.95, "change": 0, "pChange": 0, "numberOfContractsTraded": 0, "totalTurnover": 0, "nse_identifier": "OPTIDXNIFTY06-03-2025CE21350.00", "Support": null, "Resistance": "22880.95"}, {"01.03.2025": "Put24750", "instrumentType": "Index Options", "expiryDate": "06-Mar-2025", "optionType": "Put", "strikePrice": 24750, "openPrice": 0, "highPrice": 0, "lowPrice": 0, "closePrice": 1869.15, "prevClose": 1869.15, "lastPrice": 1869.15, "change": 0, "pChange": 0, "numberOfContractsTraded": 0, "totalTurnover": 0, "nse_identifier": "OPTIDXNIFTY06-03-2025PE24750.00", "Support": "22880.85", "Resistance": null}], "summary": {"open": 22433.4, "high": 22450.35, "low": 22104.85, "close": 22124.7}}